{
    "data": [
        {
            "category": "Hip-Hop", 
            "goal": "10000.0", 
            "title": "MC Lars - \"The Zombie Dinosaur LP\" by Horris Records \u2014 Kickstarter", 
            "backers": "1,017", 
            "name": "Horris Records", 
            "currency": "USD", 
            "link": "https://www.kickstarter.com/projects/horrisrecords/mc-lars-the-zombie-dinosaur-lp/", 
            "location": "Los Angeles, CA", 
            "totalPledged": "42213.35", 
            "description": "Help MC Lars independently finish & release his fourth album \"The Zombie Dinosaur LP\", intellectual hip-hop for the punk rock set."
        }, 
        {
            "category": "Hip-Hop", 
            "goal": "6000.0", 
            "title": "Joey Batts & Them - Album #2 by joey #bestfriend batts \u2014 Kickstarter", 
            "backers": "144", 
            "name": "joey #bestfriend batts", 
            "currency": "USD", 
            "link": "https://www.kickstarter.com/projects/621051274/joey-batts-and-them-album-2/", 
            "location": "Hartford, CT", 
            "totalPledged": "7234.0", 
            "description": "Help Joey Batts & Them make their sophomore album!"
        }, 
        {
            "category": "Hip-Hop", 
            "goal": "1100.0", 
            "title": "Dopus Pennington - SolidStreamofConsciousness by RJ Jackson \u2014 Kickstarter", 
            "backers": "7", 
            "name": "RJ Jackson", 
            "currency": "USD", 
            "link": "https://www.kickstarter.com/projects/dopuspenn/dopus-pennington-solidstreamofconsciousness/", 
            "location": "Birmingham, AL", 
            "totalPledged": "140.0", 
            "description": "Second Full-Length. A collection of thoughts and insights, but at the same time fun and enjoyable."
        }, 
        {
            "category": "Hip-Hop", 
            "goal": "500.0", 
            "title": "Project: AWAKE by Madd Matt \u2014 Kickstarter", 
            "backers": "6", 
            "name": "Madd Matt", 
            "currency": "USD", 
            "link": "https://www.kickstarter.com/projects/1462487424/project-awake/", 
            "location": "Faribault, MN", 
            "totalPledged": "111.0", 
            "description": "The time is now! AWAKE! Once we reach the goal, the new album will be completely set in motion. Studio, distribution, graphic design."
        }, 
        {
            "category": "Hip-Hop", 
            "goal": "15000.0", 
            "title": "Black Ink Over Dead Presidents by Brandon -Lewi B- Lewis \u2014 Kickstarter", 
            "backers": "2", 
            "name": "Brandon -Lewi B- Lewis", 
            "currency": "USD", 
            "link": "https://www.kickstarter.com/projects/2084285658/black-ink-over-dead-presidents/", 
            "location": "Evansville, IN", 
            "totalPledged": "11.0", 
            "description": "Black Ink Over Dead Presidents is describing the current time we are facing from a artists point of view as the president."
        }, 
        {
            "category": "Hip-Hop", 
            "goal": "15000.0", 
            "title": "THE EVICTION NOTICE by Akinsola Fajimolu \u2014 Kickstarter", 
            "backers": "2", 
            "name": "Akinsola Fajimolu", 
            "currency": "USD", 
            "link": "https://www.kickstarter.com/projects/706465278/the-eviction-notice/", 
            "location": "Chicago, IL", 
            "totalPledged": "10.0", 
            "description": "I WAS EVICTED. I WANT TO TALK ABOUT THIS IN A HIP HOP  ALBUM AND I NEED TO FUND THE PROJECT WITH A RECORDING BUDGET AND VIDEO BUDGET."
        }, 
        {
            "category": "Hip-Hop", 
            "goal": "8000.0", 
            "title": "#blastoff by Brandon Sharper \u2014 Kickstarter", 
            "backers": "2", 
            "name": "Brandon Sharper", 
            "currency": "USD", 
            "link": "https://www.kickstarter.com/projects/1173708975/the-inscrutable-ballads-of-a-rebel-ep/", 
            "location": "Pasadena, MD", 
            "totalPledged": "11.0", 
            "description": "former marine looks 2 tell his story of moving from state 2 state growing up and how it all changed moving 2 the world's prison capital"
        }, 
        {
            "category": "Hip-Hop", 
            "goal": "10000.0", 
            "title": "\"Amsterdam Coffee Shop\" The Debut Album by Jamil Jackson \u2014 Kickstarter", 
            "backers": "1", 
            "name": "Jamil Jackson", 
            "currency": "USD", 
            "link": "https://www.kickstarter.com/projects/2047785171/amsterdam-coffee-shop-the-debut-album/", 
            "location": "Hartford, CT", 
            "totalPledged": "15.0", 
            "description": "Name's Double G Chi (Chee) I'm an upcoming artist, born and raised in Hartford, CT, Help support my debut LP \"Amsterdam Coffee Shop\""
        }, 
        {
            "category": "Hip-Hop", 
            "goal": "1500.0", 
            "title": "Who said GREATNESS had to be mainstream?? by Jus Chris \u2014 Kickstarter", 
            "backers": "1", 
            "name": "Jus Chris", 
            "currency": "USD", 
            "link": "https://www.kickstarter.com/projects/2012530965/who-said-greatness-had-to-be-mainstream/", 
            "location": "Chicago, IL", 
            "totalPledged": "5.0", 
            "description": "I'm a poet at heart. But I make great music. I love to perform, but a great show can be expensive. But its SO worth it."
        }, 
        {
            "category": "Hip-Hop", 
            "goal": "15000.0", 
            "title": "Hip Hop, oh yeah, I forgot by Allene Lewis \u2014 Kickstarter", 
            "backers": "1", 
            "name": "Allene Lewis", 
            "currency": "USD", 
            "link": "https://www.kickstarter.com/projects/1790733335/hip-hop-oh-yeah-i-forgot/", 
            "location": "Sacramento, CA", 
            "totalPledged": "5.0", 
            "description": "Hip Hop saved me, so now I'm going to save Hip Hop."
        }, 
        {
            "category": "Hip-Hop", 
            "goal": "1000.0", 
            "title": "Louis Cheese - Litter And Ashes by Louis Turcio \u2014 Kickstarter", 
            "backers": "1", 
            "name": "Louis Turcio", 
            "currency": "USD", 
            "link": "https://www.kickstarter.com/projects/153592555/louis-cheese-litter-and-ashes/", 
            "location": "New Haven, CT", 
            "totalPledged": "20.0", 
            "description": "A cd full of great songs with a different flow. Trying to put out a free cd, dont have the funds. I LOVE MUSIC! its costly but lovely."
        }, 
        {
            "category": "Hip-Hop", 
            "goal": "1000.0", 
            "title": "Hooked on Kronix is launching their debut EP! by Hooked on Kronix \u2014 Kickstarter", 
            "backers": "11", 
            "name": "Hooked on Kronix", 
            "currency": "USD", 
            "link": "https://www.kickstarter.com/projects/933058494/hooked-on-kronix-is-launching-their-debut-ep/", 
            "location": "Pittsburgh, PA", 
            "totalPledged": "228.0", 
            "description": "Hooked on Kronix, a unique Pittsburgh based music group unlike anything you've ever heard is releasing their first official EP!"
        }, 
        {
            "category": "Hip-Hop", 
            "goal": "7000.0", 
            "title": "\"Ghetto Rhymin'\": Divine's Official Debut Hip-Hop/Rap Album by Divine \u2014 Kickstarter", 
            "backers": "19", 
            "name": "Divine", 
            "currency": "USD", 
            "link": "https://www.kickstarter.com/projects/divine/ghetto-rhymin-divines-official-debut-hip-hop-rap-a/", 
            "location": "New York, NY", 
            "totalPledged": "7021.0", 
            "description": "Pure classic Hip-Hop at its finest. Hard beats and ill rhymes from the mind of a conscious, positive, lyrical and street-edged emcee."
        }, 
        {
            "category": "Hip-Hop", 
            "goal": "800.0", 
            "title": "Man of the Hour 2 by Cazmir \u2014 Kickstarter", 
            "backers": "0", 
            "name": "Cazmir", 
            "currency": "USD", 
            "link": "https://www.kickstarter.com/projects/1754175088/man-of-the-hour-2/", 
            "location": "San Angelo, TX", 
            "totalPledged": "0.0", 
            "description": "After 2 and a half years of sharping my skills I am now ready for the second installment of the 'Man of the Hour' mixtape series."
        }, 
        {
            "category": "Hip-Hop", 
            "goal": "7000.0", 
            "title": "The Good, The Bad, and The Northside by Kabelo Dobosu II \u2014 Kickstarter", 
            "backers": "1", 
            "name": "Kabelo Dobosu II", 
            "currency": "USD", 
            "link": "https://www.kickstarter.com/projects/756055896/the-godd-the-bad-and-the-northside/", 
            "location": "Columbus, OH", 
            "totalPledged": "25.0", 
            "description": "22 yr old Northside Columbus, OH Native \"so far from where i came from and yet so close to where i need to be... 1 Mile from Heaven\""
        }, 
        {
            "category": "Hip-Hop", 
            "goal": "2000.0", 
            "title": "THE SLIM CASE vol.1 by WARREN, MEYER G \u2014 Kickstarter", 
            "backers": "2", 
            "name": "WARREN, MEYER G", 
            "currency": "USD", 
            "link": "https://www.kickstarter.com/projects/834747180/the-slim-case-vol2/", 
            "location": "St. Paul, MN", 
            "totalPledged": "15.0", 
            "description": "St. Paul Slim: The Slim Case is a very solid, very powerful EP."
        }, 
        {
            "category": "Hip-Hop", 
            "goal": "650.0", 
            "title": "SICKER THAN YOUR AVERAGE: The Chicago Cypher by Christine Ahamefule \u2014 Kickstarter", 
            "backers": "2", 
            "name": "Christine Ahamefule", 
            "currency": "USD", 
            "link": "https://www.kickstarter.com/projects/413146128/sicker-than-your-average-the-chicago-cypher/", 
            "location": "San Francisco, CA", 
            "totalPledged": "45.0", 
            "description": "SickerThanYourAvg.com, a growing Hip-Hop blog, wants to put on a (positive) Hip-Hop cypher in Chicago; a city teeming with fresh talent"
        }, 
        {
            "category": "Hip-Hop", 
            "goal": "75000.0", 
            "title": "IS IT THE SHOES?? by Ambition (deleted) \u2014 Kickstarter", 
            "backers": "0", 
            "name": "Ambition (deleted)", 
            "currency": "USD", 
            "link": "https://www.kickstarter.com/projects/1111193370/is-it-the-shoes/", 
            "location": "Harvey, LA", 
            "totalPledged": "0.0", 
            "description": "Re-Launch street smash \"Is it the Shoes\" (Reloaded) by Mpiya Entertainment!!"
        }, 
        {
            "category": "Hip-Hop", 
            "goal": "6000.0", 
            "title": "soCro's debut album: \"Eurotrash Meets Southern Class\" by soCro \u2014 Kickstarter", 
            "backers": "121", 
            "name": "soCro", 
            "currency": "USD", 
            "link": "https://www.kickstarter.com/projects/socro/socros-debut-album-eurotrash-meets-southern-class/", 
            "location": "Chattanooga, TN", 
            "totalPledged": "6438.52", 
            "description": "Help soCro release his debut album, \"Eurotrash Meets Southern Class.\""
        }, 
        {
            "category": "Hip-Hop", 
            "goal": "1800.0", 
            "title": "Darnell - Expos\u00e9 (debut album) by Darnell Bland Jr. \u2014 Kickstarter", 
            "backers": "3", 
            "name": "Darnell Bland Jr.", 
            "currency": "USD", 
            "link": "https://www.kickstarter.com/projects/849579417/darnell-expose-debut-album/", 
            "location": "Indianapolis, IN", 
            "totalPledged": "40.0", 
            "description": "Expos\u00e9 is real and raw. Darnell is serving up everything from club hits to classic R&B in his debut full-length record."
        }, 
        {
            "category": "Hip-Hop", 
            "goal": "7000.0", 
            "title": "The Midwest Massacre by Chris \"The River King\" Blake \u2014 Kickstarter", 
            "backers": "0", 
            "name": "Chris \"The River King\" Blake", 
            "currency": "USD", 
            "link": "https://www.kickstarter.com/projects/1400326624/the-midwest-massacre/", 
            "location": "Tell City, IN", 
            "totalPledged": "0.0", 
            "description": "The Midwest Massacre is a Both a Mixtape and a Full on Project. Compiling artists from around the Midwest."
        }, 
        {
            "category": "Hip-Hop", 
            "goal": "20000.0", 
            "title": "K-aos Turn Up Tour by Isiah \"K-aos\" Echevarria \u2014 Kickstarter", 
            "backers": "0", 
            "name": "Isiah \"K-aos\" Echevarria", 
            "currency": "USD", 
            "link": "https://www.kickstarter.com/projects/1568295961/k-aos-turn-up-tour/", 
            "location": "Nyack, NY", 
            "totalPledged": "0.0", 
            "description": "K-AOS is ready to \u201cTURN UP\u201d in a city near you in 2014! looks to underground fans to help fund first national tour."
        }, 
        {
            "category": "Hip-Hop", 
            "goal": "1000.0", 
            "title": "Rob Dorsey- The Ralphie Tapes by Rob Dorsey \u2014 Kickstarter", 
            "backers": "1", 
            "name": "Rob Dorsey", 
            "currency": "USD", 
            "link": "https://www.kickstarter.com/projects/mrrobdorsey/rob-dorsey-the-ralphie-tapes", 
            "location": "New Castle, DE", 
            "totalPledged": "100.0", 
            "description": "This Project is to be a full mental release of My personal views on such concepts as Love, Life, Government and Religion."
        }, 
        {
            "category": "Hip-Hop", 
            "goal": "2500.0", 
            "title": "Nathan Clapper's First Professionally Produced Record by littleFoundry \u2014 Kickstarter", 
            "backers": "9", 
            "name": "littleFoundry", 
            "currency": "USD", 
            "link": "https://www.kickstarter.com/projects/littlefoundry/nathan-clappers-first-professionally-produced-reco/", 
            "location": "Columbus, OH", 
            "totalPledged": "421.0", 
            "description": "Help support Nathan through his studio journey with producer Craig Bauer from Chicago, IL."
        }, 
        {
            "category": "Hip-Hop", 
            "goal": "5000.0", 
            "title": "operation | Respect the Midwest - J-Rell feat TEN ARTISTS!!! by Nicole Alvarez & Kareen Wright \u2014 Kickstarter", 
            "backers": "4", 
            "name": "Nicole Alvarez & Kareen Wright", 
            "currency": "USD", 
            "link": "https://www.kickstarter.com/projects/89025951/operation-respect-the-midwest-j-rell-feat-ten-arti/", 
            "location": "Chicago, IL", 
            "totalPledged": "105.0", 
            "description": "Chicago Producer J-Rell is crafting an amazing song w/ 10 Midwest Artists to influence a POWERFUL, UNIFIED HIP-HOP MOVEMENT!!!!"
        }, 
        {
            "category": "Hip-Hop", 
            "goal": "10000.0", 
            "title": "DA MILLION DOLLA BABBY by CHRISTOPHER D. ASHLEY \u2014 Kickstarter", 
            "backers": "0", 
            "name": "CHRISTOPHER D. ASHLEY", 
            "currency": "USD", 
            "link": "https://www.kickstarter.com/projects/790498533/da-million-dolla-babby/", 
            "location": "Chicago, IL", 
            "totalPledged": "0.0", 
            "description": "TRIUMPHANT"
        }, 
        {
            "category": "Hip-Hop", 
            "goal": "35000.0", 
            "title": "The Debut Album \"For What Its Worth\" by Big Homie Snubs \u2014 Kickstarter", 
            "backers": "0", 
            "name": "Big Homie Snubs", 
            "currency": "USD", 
            "link": "https://www.kickstarter.com/projects/1484436881/the-debut-album-for-what-its-worth/", 
            "location": "Marietta, GA", 
            "totalPledged": "0.0", 
            "description": "This project will give my life's trials and tribulations of my path from a growing boy to a man. Find out how you can be apart of it!"
        }, 
        {
            "category": "Hip-Hop", 
            "goal": "50000.0", 
            "title": "The Will to Win by Kevin Bentley \u2014 Kickstarter", 
            "backers": "2", 
            "name": "Kevin Bentley", 
            "currency": "USD", 
            "link": "https://www.kickstarter.com/projects/939716986/the-will-to-win/", 
            "location": "Houston, TX", 
            "totalPledged": "10.0", 
            "description": "Music that's been inspired by my life that I know the world can relate to !! Hopefully we can bring it to the world together !!"
        }, 
        {
            "category": "Hip-Hop", 
            "goal": "1500.0", 
            "title": "Golden Muse, Cosmic Sounds by Gold Lauderdale \u2014 Kickstarter", 
            "backers": "1", 
            "name": "Gold Lauderdale", 
            "currency": "USD", 
            "link": "https://www.kickstarter.com/projects/ahayahgold/golden-muse-cosmic-sounds/", 
            "location": "Sacramento, CA", 
            "totalPledged": "15.0", 
            "description": "Here to take artistry to a COSMIC level and just BE who I AM..!"
        }, 
        {
            "category": "Hip-Hop", 
            "goal": "10000.0", 
            "title": "\" Sunset 2 Sunrise\" by Raymon A. Marines \u2014 Kickstarter", 
            "backers": "4", 
            "name": "Raymon A. Marines", 
            "currency": "USD", 
            "link": "https://www.kickstarter.com/projects/116190323/sunset-2-sunrise/", 
            "location": "Tucson, AZ", 
            "totalPledged": "125.0", 
            "description": "It is a full length album titled \"Sunset 2 Sunrise\"about my life with Classical, Jazz & Blues rhythm over Hip Hop drums & chill lyrics."
        }, 
        {
            "category": "Hip-Hop", 
            "goal": "4000.0", 
            "title": "The Vacation by Boogie P \u2014 Kickstarter", 
            "backers": "1", 
            "name": "Boogie P", 
            "currency": "USD", 
            "link": "https://www.kickstarter.com/projects/507835322/the-vacation/", 
            "location": "Detroit, MI", 
            "totalPledged": "3.0", 
            "description": "New project by local Detroit artist Boogie P. The Vacation is full of great music with songs like \"Disco\" and \"Lauren\"."
        }, 
        {
            "category": "Hip-Hop", 
            "goal": "1000.0", 
            "title": "My first album by Daniel Big-Red Goren \u2014 Kickstarter", 
            "backers": "3", 
            "name": "Daniel Big-Red Goren", 
            "currency": "USD", 
            "link": "https://www.kickstarter.com/projects/800659069/my-first-album-1/", 
            "location": "Worcester, MA", 
            "totalPledged": "45.0", 
            "description": "I would like to get enough money possible to copyright, promote and distribute my first album of instrumentals."
        }, 
        {
            "category": "Hip-Hop", 
            "goal": "1000.0", 
            "title": "\"N Wordz N Music\" by Danny Pearson \u2014 Kickstarter", 
            "backers": "1", 
            "name": "Danny Pearson", 
            "currency": "USD", 
            "link": "https://www.kickstarter.com/projects/dpnlife/n-wordz-n-music/", 
            "location": "Stonewall, MS", 
            "totalPledged": "1.0", 
            "description": "My second studio album and latest music venture, which  explores  the thought provoking power of Acoustic Neo-Soul\""
        }, 
        {
            "category": "Hip-Hop", 
            "goal": "1250.0", 
            "title": "Conviction by A.G. \u2014 Kickstarter", 
            "backers": "0", 
            "name": "A.G.", 
            "currency": "USD", 
            "link": "https://www.kickstarter.com/projects/355426684/conviction/", 
            "location": "Corpus Christi, TX", 
            "totalPledged": "0.0", 
            "description": "Be a part of indie artist/producer A.G. completing his next project, \"Conviction\". Chasing a dream that revolves around my King. Jesus."
        }, 
        {
            "category": "Hip-Hop", 
            "goal": "12000.0", 
            "title": "Mass Production of \"Thug Royalty\" the debut album. by Cory Brown \u2014 Kickstarter", 
            "backers": "0", 
            "name": "Cory Brown", 
            "currency": "USD", 
            "link": "https://www.kickstarter.com/projects/unsignedhype/mass-production-of-thug-royalty-the-debut-album/", 
            "location": "York, PA", 
            "totalPledged": "0.0", 
            "description": "This project'll bring real rap to all hip hop lovers. I'm a dedicated artist that will open the minds & hearts of my fans Thug Royalty\""
        }, 
        {
            "category": "Hip-Hop", 
            "goal": "1100.0", 
            "title": "Atiq The Tru Story CD Distribution by Atiq Story \u2014 Kickstarter", 
            "backers": "2", 
            "name": "Atiq Story", 
            "currency": "USD", 
            "link": "https://www.kickstarter.com/projects/atiq/atiq-the-tru-story-cd-distribution/", 
            "location": "Fort Wayne, IN", 
            "totalPledged": "15.0", 
            "description": "A way to help this artist distribute professional cd's of his first album, continue the work on his second, and possibly much more"
        }, 
        {
            "category": "Hip-Hop", 
            "goal": "1000.0", 
            "title": "Bring Ayhay to Detroit by Stewart Artist Management \u2014 Kickstarter", 
            "backers": "4", 
            "name": "Stewart Artist Management", 
            "currency": "USD", 
            "link": "https://www.kickstarter.com/projects/1889504226/bring-ayhay-to-detroit/", 
            "location": "Warren, MI", 
            "totalPledged": "73.0", 
            "description": "REDD is having a mixtape release party at the Detroit Pub. We want to bring Ayhay to Detroit to play their song \"Know it's Real\""
        }, 
        {
            "category": "Hip-Hop", 
            "goal": "750.0", 
            "title": "Amerikas Addiction  -   'Late Nights Early Mornings'  #DWYD by Brett Wenthur \u2014 Kickstarter", 
            "backers": "29", 
            "name": "Brett Wenthur", 
            "currency": "USD", 
            "link": "https://www.kickstarter.com/projects/amerikasaddiction/amerikas-addiction-late-nights-early-mornings-dwyd/", 
            "location": "Milwaukee, WI", 
            "totalPledged": "1333.0", 
            "description": "Amerikas Addiction wants to connect and become closer to all of our addicts with this project, not only musically but in general #dwyd"
        }, 
        {
            "category": "Hip-Hop", 
            "goal": "2000.0", 
            "title": "Project RaB by JayLa Inc \u2014 Kickstarter", 
            "backers": "0", 
            "name": "JayLa Inc", 
            "currency": "USD", 
            "link": "https://www.kickstarter.com/projects/jaylainc/project-rab/", 
            "location": "Atlanta, GA", 
            "totalPledged": "0.0", 
            "description": "Come Experience Project RaB or Project R.a.B. .JayLa Inc's Independent Artist From St. Petersburg,FL With A Organic Sound !"
        }, 
        {
            "category": "Hip-Hop", 
            "goal": "100000.0", 
            "title": "Scribble Jam 2014 by Nick Accurso + Mr. Dibbs \u2014 Kickstarter", 
            "backers": "116", 
            "name": "Nick Accurso + Mr. Dibbs", 
            "currency": "USD", 
            "link": "https://www.kickstarter.com/projects/1358010004/scribble-jam-2014/", 
            "location": "Cincinnati, OH", 
            "totalPledged": "11325.3", 
            "description": "\"AMERICA'S LARGEST HIP HOP FESTIVAL\"Emcee Battle+DJ Battle+B-Boy Battle+Beatbox Battle+Graffiti Expo+50 Live Performances"
        }, 
        {
            "category": "Hip-Hop", 
            "goal": "2000.0", 
            "title": "iP\u039bT's Next Single! by iP\u039bT \u2014 Kickstarter", 
            "backers": "2", 
            "name": "iP\u039bT", 
            "currency": "USD", 
            "link": "https://www.kickstarter.com/projects/550852112/ipts-next-single/", 
            "location": "Hyattsville, MD", 
            "totalPledged": "110.0", 
            "description": "Support a local DMV artist in the making of his next Masterpiece!"
        }, 
        {
            "category": "Hip-Hop", 
            "goal": "300.0", 
            "title": "Dez Brown - Military Music by Dez Brown (deleted) \u2014 Kickstarter", 
            "backers": "0", 
            "name": "Dez Brown (deleted)", 
            "currency": "USD", 
            "link": "https://www.kickstarter.com/projects/dbrown5400/dez-brown-military-music/", 
            "location": "Atlanta, GA", 
            "totalPledged": "0.0", 
            "description": "MY New EP Military Music Is Available On ITunes. This Project Is Self Funded,And Independently Distrubuted,Music Videos Coming Soon"
        }, 
        {
            "category": "Hip-Hop", 
            "goal": "40000.0", 
            "title": "The \"Forever Land\" Project by Christian Parker \u2014 Kickstarter", 
            "backers": "0", 
            "name": "Christian Parker", 
            "currency": "USD", 
            "link": "https://www.kickstarter.com/projects/781611795/the-forever-land-project/", 
            "location": "Lubbock, TX", 
            "totalPledged": "0.0", 
            "description": "A-Trip music 2014. Get ready for a new vision. \"Forever Land\" w/ special guests."
        }, 
        {
            "category": "Hip-Hop", 
            "goal": "7000.0", 
            "title": "Do You Love Me? by Nique \u2014 Kickstarter", 
            "backers": "4", 
            "name": "Nique", 
            "currency": "USD", 
            "link": "https://www.kickstarter.com/projects/thenique/do-you-love-me/", 
            "location": "Houston, TX", 
            "totalPledged": "180.0", 
            "description": "Nique's releasing his EP \"Do You Love Me?\" influenced by chillwave, horror movies, and matters of the heart."
        }, 
        {
            "category": "Hip-Hop", 
            "goal": "2500.0", 
            "title": "\"Potent Product\" Promotion Tour. Supporting The People. by Sincere Davinci \u2014 Kickstarter", 
            "backers": "0", 
            "name": "Sincere Davinci", 
            "currency": "USD", 
            "link": "https://www.kickstarter.com/projects/68540041/potent-product-promotion-tour-supporting-the-peopl/", 
            "location": "Brooklyn, NY", 
            "totalPledged": "0.0", 
            "description": "In todays INDY world, connecting with the people is what will sustain you. I'm simply trying to reach those supporters outside of NY."
        }, 
        {
            "category": "Hip-Hop", 
            "goal": "3700.0", 
            "title": "20 Grand's First Album by Rebecca Nelson \u2014 Kickstarter", 
            "backers": "68", 
            "name": "Rebecca Nelson", 
            "currency": "USD", 
            "link": "https://www.kickstarter.com/projects/1414315812/20-grands-first-album/", 
            "location": "Whitefish, MT", 
            "totalPledged": "5376.0", 
            "description": "Montana's 20 Grand, your friendly neighborhood funk band, has recorded 11 original songs, and is starting to take the next steps."
        }, 
        {
            "category": "Hip-Hop", 
            "goal": "10000.0", 
            "title": "All Out Hustle The Album by All Out Hustle \u2014 Kickstarter", 
            "backers": "0", 
            "name": "All Out Hustle", 
            "currency": "USD", 
            "link": "https://www.kickstarter.com/projects/1115801495/all-out-hustle-the-album/", 
            "location": "Miami, FL", 
            "totalPledged": "0.0", 
            "description": "An Album Showcasing Local Upcoming Artists & Creating New Opportunities in the Community"
        }, 
        {
            "category": "Hip-Hop", 
            "goal": "30000.0", 
            "title": "Welcome 2 Tauntville by Taunt \u2014 Kickstarter", 
            "backers": "0", 
            "name": "Taunt", 
            "currency": "USD", 
            "link": "https://www.kickstarter.com/projects/99433086/welcome-2-tauntville/", 
            "location": "South Jacksonville, Jacksonville, FL", 
            "totalPledged": "0.0", 
            "description": "Welcome 2 TAUNTVILLE"
        }, 
        {
            "category": "Hip-Hop", 
            "goal": "5000.0", 
            "title": "Uplift Group EXACT by christopher simon \u2014 Kickstarter", 
            "backers": "2", 
            "name": "christopher simon", 
            "currency": "USD", 
            "link": "https://www.kickstarter.com/projects/92887809/uplift-group-exact/", 
            "location": "New York, NY", 
            "totalPledged": "2.0", 
            "description": "Kid Rappers/ Singers uplifting , concious , Fun"
        }, 
        {
            "category": "Hip-Hop", 
            "goal": "15000.0", 
            "title": "Derek V. - The journey to \"Vices, Vixens, and Villains\". by Derek V. \u2014 Kickstarter", 
            "backers": "2", 
            "name": "Derek V.", 
            "currency": "USD", 
            "link": "https://www.kickstarter.com/projects/1399963652/derek-v-the-journey-to-vices-vixens-and-villains/", 
            "location": "San Francisco, CA", 
            "totalPledged": "51.0", 
            "description": "New name. New album. Same Villainy."
        }, 
        {
            "category": "Hip-Hop", 
            "goal": "5000.0", 
            "title": "FranciisNeptune's Hood Symphony Album by Jonathan Hardin \u2014 Kickstarter", 
            "backers": "2", 
            "name": "Jonathan Hardin", 
            "currency": "USD", 
            "link": "https://www.kickstarter.com/projects/2131127239/franciisneptunes-hood-symphony-album/", 
            "location": "Asbury Park, NJ", 
            "totalPledged": "8.0", 
            "description": "This Kickstarter is to help produce Limited Edition Physical Copies for sale for the Hood Symphony Double Album in CD and Vinyl format"
        }, 
        {
            "category": "Hip-Hop", 
            "goal": "7500.0", 
            "title": "Enemy of the State.... by Demarcus Ballard \u2014 Kickstarter", 
            "backers": "0", 
            "name": "Demarcus Ballard", 
            "currency": "USD", 
            "link": "https://www.kickstarter.com/projects/163921865/enemy-of-the-state/", 
            "location": "Little Rock, AR", 
            "totalPledged": "0.0", 
            "description": "Listen to A new perspective own what it feels like to be targeted by everybody including the goverment...!!!"
        }, 
        {
            "category": "Hip-Hop", 
            "goal": "1800.0", 
            "title": "Quality OVER Quantity Demo TeamWork Makes The DreamWork by Marcus Hogue \u2014 Kickstarter", 
            "backers": "6", 
            "name": "Marcus Hogue", 
            "currency": "USD", 
            "link": "https://www.kickstarter.com/projects/hydeff/quality-over-quantity-demo-teamwork-makes-the-drea/", 
            "location": "Philadelphia, PA", 
            "totalPledged": "411.0", 
            "description": "Quality Over Quantity is exactly what the title says! Great Quality Music from a DOPE artist. Dedication with a smart work ethic."
        }, 
        {
            "category": "Hip-Hop", 
            "goal": "6000.0", 
            "title": "NOLA Hiphop Archive by Holly Hobbs \u2014 Kickstarter", 
            "backers": "182", 
            "name": "Holly Hobbs", 
            "currency": "USD", 
            "link": "https://www.kickstarter.com/projects/1536605494/nola-hiphop-archive/", 
            "location": "New Orleans, LA", 
            "totalPledged": "6173.05", 
            "description": "A digital archive of New Orleans hiphop and bounce supported by the Amistad Research Center launching Spring 2014!"
        }, 
        {
            "category": "Hip-Hop", 
            "goal": "2350.0", 
            "title": "AN[OTHER M]: A Metroid Inspired EP by Sammus \u2014 Kickstarter", 
            "backers": "230", 
            "name": "Sammus", 
            "currency": "USD", 
            "link": "https://www.kickstarter.com/projects/1333819586/an-other-m-a-metroid-inspired-ep/", 
            "location": "Ithaca, NY", 
            "totalPledged": "4705.32", 
            "description": "Join rapper and producer Sammus as she creates a seven-track Metroid inspired EP with original beats, lyrics, and art!"
        }, 
        {
            "category": "Hip-Hop", 
            "goal": "3295.0", 
            "title": "\"Fuck Every Body\" by Manoa Cubos \u2014 Kickstarter", 
            "backers": "1", 
            "name": "Manoa Cubos", 
            "currency": "USD", 
            "link": "https://www.kickstarter.com/projects/587783717/fuck-every-body/", 
            "location": "Clovis, CA", 
            "totalPledged": "10.0", 
            "description": "Creating my 3rd mixtape."
        }, 
        {
            "category": "Hip-Hop", 
            "goal": "15000.0", 
            "title": "Christian Radke \"Fatal Attraction\" Tour by John \"Jmacdaddy\" Anderson \u2014 Kickstarter", 
            "backers": "4", 
            "name": "John \"Jmacdaddy\" Anderson", 
            "currency": "USD", 
            "link": "https://www.kickstarter.com/projects/christianradke/christian-radke-fatal-attraction-tour/", 
            "location": "New Orleans, LA", 
            "totalPledged": "160.0", 
            "description": "The chance to be apart of the next HipHop/R&B movement from New Orleans headed by Singer Christian Radke"
        }
    ]
}