{
    "data": [
        {
            "category": "Kids", 
            "goal": "2900.0", 
            "title": "Bring Know Orchestra to Boston Area Kids by Know Orchestra \u2014 Kickstarter", 
            "backers": "43", 
            "name": "Know Orchestra", 
            "currency": "USD", 
            "link": "https://www.kickstarter.com/projects/975536542/bring-know-orchestra-to-boston-area-kids/", 
            "location": "Boston, MA", 
            "totalPledged": "5135.0", 
            "description": "With your support, Know Orchestra is seeking to bring its interactive and educational live show to children in underserved communities."
        }
    ]
}