{
    "data": [
        {
            "category": "Poetry", 
            "goal": "7500.0", 
            "title": "Papa Possum's First Little Book of Satires by Papa Possum \u2014 Kickstarter", 
            "backers": "13", 
            "name": "Papa Possum", 
            "currency": "USD", 
            "link": "https://www.kickstarter.com/projects/papapossum/papa-possums-first-little-book-of-satires/", 
            "location": "Woodbury, CT", 
            "totalPledged": "1065.0", 
            "description": "The 1st book by American political satirist Papa Possum. 14 original satires in verse with accompanying illustrations and notations."
        }, 
        {
            "category": "Poetry", 
            "goal": "9000.0", 
            "title": "A Brooklyn Project by Kimberley Celeste Penamon \u2014 Kickstarter", 
            "backers": "7", 
            "name": "Kimberley Celeste Penamon", 
            "currency": "USD", 
            "link": "https://www.kickstarter.com/projects/penamonperks/a-brooklyn-project/", 
            "location": "Memphis, TN", 
            "totalPledged": "66.0", 
            "description": "\"A Brooklyn Project\" an urban book of poetry from the authors perspective of living in Farragut Projects located in Brooklyn, NYC."
        }, 
        {
            "category": "Poetry", 
            "goal": "12600.0", 
            "title": "A Treasure Trove of Rhyme, coffee table sized / gift quality by Mark Stellinga \u2014 Kickstarter", 
            "backers": "1", 
            "name": "Mark Stellinga", 
            "currency": "USD", 
            "link": "https://www.kickstarter.com/projects/1521510912/a-treasure-trove-of-rhyme-coffee-table-sized-gift/", 
            "location": "Tiffin, IA", 
            "totalPledged": "40.0", 
            "description": "Thought provoking rhyming tales, in a unique LANDSCAPE ORIENTED, HC book. A culmination of 50+ years of penning quality rhyme. 370 pgs."
        }, 
        {
            "category": "Poetry", 
            "goal": "2625.0", 
            "title": "Poetry Crossing, from California Poets in the Schools by Phyllis Meshulam \u2014 Kickstarter", 
            "backers": "90", 
            "name": "Phyllis Meshulam", 
            "currency": "USD", 
            "link": "https://www.kickstarter.com/projects/413315824/poetry-crossing-from-california-poets-in-the-schoo/", 
            "location": "Sebastopol, CA", 
            "totalPledged": "3972.0", 
            "description": "Collected lesson plans for CPitS' 50 years. Phil Levine: \"All ...who love poetry are in debt to those who worked with these children.\""
        }, 
        {
            "category": "Poetry", 
            "goal": "200.0", 
            "title": "Paper Dreams by Carlos A. Pi\u00f1\u00f3n \u2014 Kickstarter", 
            "backers": "19", 
            "name": "Carlos A. Pi\u00f1\u00f3n", 
            "currency": "USD", 
            "link": "https://www.kickstarter.com/projects/1125035603/paper-dreams-0/", 
            "location": "Chicago, IL", 
            "totalPledged": "372.0", 
            "description": "Paper Dreams is a collection of writings ranging from poetry to prose to playwright. I started four years ago--it's time to publish."
        }, 
        {
            "category": "Poetry", 
            "goal": "800.0", 
            "title": "Return to Mykonos poetry chapbook by Iven Lourie \u2014 Kickstarter", 
            "backers": "17", 
            "name": "Iven Lourie", 
            "currency": "USD", 
            "link": "https://www.kickstarter.com/projects/2072737490/return-to-mykonos-poetry-chapbook/", 
            "location": "Sacramento, CA", 
            "totalPledged": "900.0", 
            "description": "Two sequences: Poems from a Greek Journal (1972) and Return to Mykonos (1998) with author's watercolors make up this 40-page chapbook."
        }, 
        {
            "category": "Poetry", 
            "goal": "600.0", 
            "title": "Nikki's Book: Skin-Traced Constellations by Nikki Burian \u2014 Kickstarter", 
            "backers": "19", 
            "name": "Nikki Burian", 
            "currency": "USD", 
            "link": "https://www.kickstarter.com/projects/482907326/nikkis-book-skin-traced-constellations/", 
            "location": "Portland, OR", 
            "totalPledged": "875.0", 
            "description": "Putting my poetry into a book is my biggest dream. I am so close to realizing it, I can practically feel the book in my hands."
        }, 
        {
            "category": "Poetry", 
            "goal": "300.0", 
            "title": "SENTENCES, Volume IV by Chris Belden \u2014 Kickstarter", 
            "backers": "26", 
            "name": "Chris Belden", 
            "currency": "USD", 
            "link": "https://www.kickstarter.com/projects/1522882778/sentences-volume-iv/", 
            "location": "Ridgefield, CT", 
            "totalPledged": "582.0", 
            "description": "Prose & poetry by the inmates of Garner Correctional Institution, a maximum security prison in Connecticut."
        }, 
        {
            "category": "Poetry", 
            "goal": "8500.0", 
            "title": "Publishing My New Book: Brown Skin and the Beautiful Faith by Terry E. Carter \u2014 Kickstarter", 
            "backers": "138", 
            "name": "Terry E. Carter", 
            "currency": "USD", 
            "link": "https://www.kickstarter.com/projects/1982794170/publishing-my-new-book-brown-skin-and-the-beautifu/", 
            "location": "Randolph, MA", 
            "totalPledged": "8936.0", 
            "description": "I'm publishing my 2nd book in a trilogy of Christian-inspired poetry. It's called \"Brown Skin and the Beautiful Faith\". Want to help?"
        }, 
        {
            "category": "Poetry", 
            "goal": "1100.0", 
            "title": "January Found: A Book of Poems and Performance Scores by Michael Sikkema \u2014 Kickstarter", 
            "backers": "53", 
            "name": "Michael Sikkema", 
            "currency": "USD", 
            "link": "https://www.kickstarter.com/projects/709333033/january-found-a-book-of-poems-and-performance-scor/", 
            "location": "Grand Rapids, MI", 
            "totalPledged": "1153.0", 
            "description": "January Found is a book of poems and performance pieces, many of which have been published in journals and in chapbook form."
        }, 
        {
            "category": "Poetry", 
            "goal": "4000.0", 
            "title": "An Island on the Page by Martha's Vineyard Poetry Society \u2014 Kickstarter", 
            "backers": "9", 
            "name": "Martha's Vineyard Poetry Society", 
            "currency": "USD", 
            "link": "https://www.kickstarter.com/projects/295733927/an-island-on-the-page/", 
            "location": "Vineyard Haven, MA", 
            "totalPledged": "280.0", 
            "description": "How does the heart of an island beat?  Listen through the pieces."
        }, 
        {
            "category": "Poetry", 
            "goal": "100.0", 
            "title": "Andrew's Writing Haiku by Andrew Hoelscher \u2014 Kickstarter", 
            "backers": "1", 
            "name": "Andrew Hoelscher", 
            "currency": "USD", 
            "link": "https://www.kickstarter.com/projects/63503852/andrews-writing-haiku/", 
            "location": "Irving, TX", 
            "totalPledged": "1.0", 
            "description": "I'd like to publish a book of haiku, I just need topics for the poems and a little cash for the publishing costs."
        }, 
        {
            "category": "Poetry", 
            "goal": "500.0", 
            "title": "Sixty Second Poetry \u2014 Vol. 1 by Chad Schomber \u2014 Kickstarter", 
            "backers": "19", 
            "name": "Chad Schomber", 
            "currency": "USD", 
            "link": "https://www.kickstarter.com/projects/chadschomber/sixty-second-poetry-vol-1", 
            "location": "Black Earth, WI", 
            "totalPledged": "536.0", 
            "description": "Sixty Second Poetry | It only takes a minute. The goal is to think quick, let emotions flow and hopefully end up with something worth."
        }, 
        {
            "category": "Poetry", 
            "goal": "300.0", 
            "title": "Condor: A Book of Poems by Sam Graebner \u2014 Kickstarter", 
            "backers": "19", 
            "name": "Sam Graebner", 
            "currency": "USD", 
            "link": "https://www.kickstarter.com/projects/359331644/condor-a-book-of-poems/", 
            "location": "Charleston, SC", 
            "totalPledged": "463.0", 
            "description": "This book encompasses my work from Spring 2011 through Winter 2013. It links creation myths and family history into personal challenges"
        }, 
        {
            "category": "Poetry", 
            "goal": "5000.0", 
            "title": "Poetically Speaking: Stories of Love, Triumph and Struggle by Tylicee Mysreign \u2014 Kickstarter", 
            "backers": "5", 
            "name": "Tylicee Mysreign", 
            "currency": "USD", 
            "link": "https://www.kickstarter.com/projects/tylicee/poetically-speaking-stories-of-love-triumph-and-st/", 
            "location": "Detroit, MI", 
            "totalPledged": "130.0", 
            "description": "Poets, artists and photographers from Detroit come together in a stunning book to share their stories of love, triumph, and struggle"
        }, 
        {
            "category": "Poetry", 
            "goal": "2000.0", 
            "title": "Sylvia Bowman's First Poetry Collection: We Met, Once Before by Irenicon Press @ The Writers' Workshoppe \u2014 Kickstarter", 
            "backers": "40", 
            "name": "Irenicon Press @ The Writers' Workshoppe", 
            "currency": "USD", 
            "link": "https://www.kickstarter.com/projects/905723151/sylvia-bowmans-first-poetry-collection-we-met-once/", 
            "location": "Port Townsend, WA", 
            "totalPledged": "2002.0", 
            "description": "Irenicon Press collects the short jewel-like poems of Sylvia Bowman into her first collection: We Met, Once Before."
        }, 
        {
            "category": "Poetry", 
            "goal": "1200.0", 
            "title": "Haikus for Gambia by IB\u00e9 \u2014 Kickstarter", 
            "backers": "45", 
            "name": "IB\u00e9", 
            "currency": "USD", 
            "link": "https://www.kickstarter.com/projects/1669238834/haikus-for-gambia/", 
            "location": "Minneapolis, MN", 
            "totalPledged": "1535.0", 
            "description": "49 poets, 49 haikus for Gambia! Everywhere on 2/18/14--billboards, radio, newspapers, the Internet! #Haikus4Gambia"
        }, 
        {
            "category": "Poetry", 
            "goal": "5000.0", 
            "title": "Poetry Book - \"Simple Thoughts\" by Christopher Michael Ross \u2014 Kickstarter", 
            "backers": "1", 
            "name": "Christopher Michael Ross", 
            "currency": "USD", 
            "link": "https://www.kickstarter.com/projects/493392836/poetry-book-simple-thoughts/", 
            "location": "Merrick, NY", 
            "totalPledged": "25.0", 
            "description": "A collection of emotional, thought-provoking poetry."
        }, 
        {
            "category": "Poetry", 
            "goal": "500.0", 
            "title": "Publish my Book of Poetry by jacob foy \u2014 Kickstarter", 
            "backers": "1", 
            "name": "jacob foy", 
            "currency": "USD", 
            "link": "https://www.kickstarter.com/projects/1979801461/publish-my-book-of-poetry/", 
            "location": "Kansas City, KS", 
            "totalPledged": "10.0", 
            "description": "I'm a poet looking to self publish my first book to get started."
        }, 
        {
            "category": "Poetry", 
            "goal": "250.0", 
            "title": "Is This Country? (2nd ed.) Reaching a wider audience... by Jesse David Chariton \u2014 Kickstarter", 
            "backers": "1", 
            "name": "Jesse David Chariton", 
            "currency": "USD", 
            "link": "https://www.kickstarter.com/projects/jessedavidchariton/is-this-country-2nd-ed-reaching-a-wider-audience", 
            "location": "Auburn, AL", 
            "totalPledged": "10.0", 
            "description": "Is This Country?, a book of poems & lyrics, is now in a 2nd edition, and trying to reach a wider audience (i.e. more than my family)."
        }, 
        {
            "category": "Poetry", 
            "goal": "2340.0", 
            "title": "Bohemian Pipe Dreams - Book of Poetry & Artwork by Drexel White \u2014 Kickstarter", 
            "backers": "1", 
            "name": "Drexel White", 
            "currency": "USD", 
            "link": "https://www.kickstarter.com/projects/drexelwhite/bohemian-pipe-dreams-book-of-poetry-and-artwork/", 
            "location": "Sale Creek, TN", 
            "totalPledged": "1.0", 
            "description": "Work influenced by Poe, Charles Baudelaire & Dante. Most focuses on philosophy, man's battle of good vs. evil & gothic romance."
        }, 
        {
            "category": "Poetry", 
            "goal": "1700.0", 
            "title": "Anthems - Poetry Collection by Jennifer Silvey \u2014 Kickstarter", 
            "backers": "17", 
            "name": "Jennifer Silvey", 
            "currency": "USD", 
            "link": "https://www.kickstarter.com/projects/535260169/anthems-poetry-collection/", 
            "location": "Springfield, MO", 
            "totalPledged": "1775.0", 
            "description": "Anthems is a poetry collection I started in grad school. It covers: dinosaurs, quantum mechanics, love, ghosts, gardens, & monsters."
        }, 
        {
            "category": "Poetry", 
            "goal": "20000.0", 
            "title": "Rare Historical Artifact: Poetry from China (1864-1954) by Evelyn Ch'ien \u2014 Kickstarter", 
            "backers": "42", 
            "name": "Evelyn Ch'ien", 
            "currency": "USD", 
            "link": "https://www.kickstarter.com/projects/1595700694/rare-historical-artifact-poetry-from-china-1864-19/", 
            "location": "Manhattan, NY", 
            "totalPledged": "20256.0", 
            "description": "This book is a collection of 600 poems written by a  diplomat (1864-1954)  who lived in China, America, Cuba, Japan and Korea."
        }, 
        {
            "category": "Poetry", 
            "goal": "600.0", 
            "title": "Help Launch Police Blotter Haiku! by Jim Jones \u2014 Kickstarter", 
            "backers": "50", 
            "name": "Jim Jones", 
            "currency": "USD", 
            "link": "https://www.kickstarter.com/projects/572102501/help-launch-police-blotter-haiku/", 
            "location": "Santa Cruz, CA", 
            "totalPledged": "1063.0", 
            "description": "The poetry of crime, in haiku form.  Hundreds of true stories of error, fear, and folly: all in one slim volume. With pictures."
        }, 
        {
            "category": "Poetry", 
            "goal": "2000.0", 
            "title": "Made from Concentration professional poetry by Nolan O'Malley \u2014 Kickstarter", 
            "backers": "2", 
            "name": "Nolan O'Malley", 
            "currency": "USD", 
            "link": "https://www.kickstarter.com/projects/1306075253/made-from-concentration-professional-poetry/", 
            "location": "Rockford, IL", 
            "totalPledged": "20.0", 
            "description": "I've published an e-book and need help making a professional hardcover book.  I write daily and need to expand into the market."
        }, 
        {
            "category": "Poetry", 
            "goal": "1800.0", 
            "title": "Publishing Prayer Poetry for those who have been there. by Annie Layer \u2014 Kickstarter", 
            "backers": "0", 
            "name": "Annie Layer", 
            "currency": "USD", 
            "link": "https://www.kickstarter.com/projects/1436468366/publishing-prayer-poetry-for-those-who-have-been-t/", 
            "location": "Daytona Beach, FL", 
            "totalPledged": "0.0", 
            "description": "I've been writing poetry since I could spell, and it is how I pray. Samples are on Facebook at Prayer Poetry."
        }, 
        {
            "category": "Poetry", 
            "goal": "800.0", 
            "title": "Omissionary by Stephen Dvorak \u2014 Kickstarter", 
            "backers": "31", 
            "name": "Stephen Dvorak", 
            "currency": "USD", 
            "link": "https://www.kickstarter.com/projects/737636692/omissionary/", 
            "location": "Chicago, IL", 
            "totalPledged": "1056.66", 
            "description": "We're publishing my first book of poetry using alternative methods focused on helping local words reach a broader audience."
        }, 
        {
            "category": "Poetry", 
            "goal": "5000.0", 
            "title": "The Ends Of The Earth: Poems by Charles Bane, Jr. by Charles Bane, Jr. \u2014 Kickstarter", 
            "backers": "0", 
            "name": "Charles Bane, Jr.", 
            "currency": "USD", 
            "link": "https://www.kickstarter.com/projects/1113175347/the-ends-of-the-earth-poems-by-charles-bane-jr/", 
            "location": "Palm Beach Gardens, FL", 
            "totalPledged": "0.0", 
            "description": "This will be my third collection of poetry, and deepest portion of a journey that has been marked by critical praise."
        }, 
        {
            "category": "Poetry", 
            "goal": "5000.0", 
            "title": "the bantership - collected poems by Harrison Parks \u2014 Kickstarter", 
            "backers": "1", 
            "name": "Harrison Parks", 
            "currency": "USD", 
            "link": "https://www.kickstarter.com/projects/91518227/the-bantership-collected-poems/", 
            "location": "Tulsa, OK", 
            "totalPledged": "1.0", 
            "description": "The bantership is a series of poems I've written over the past few years that speak to the possibilities of life after tragedy."
        }, 
        {
            "category": "Poetry", 
            "goal": "320.0", 
            "title": "Boston to Seattle; A Rough Landing Through Poems by Zac Burlingame \u2014 Kickstarter", 
            "backers": "12", 
            "name": "Zac Burlingame", 
            "currency": "USD", 
            "link": "https://www.kickstarter.com/projects/1668312867/boston-to-seattle-a-rough-landing-through-poems/", 
            "location": "Seattle, WA", 
            "totalPledged": "384.0", 
            "description": "Six months ago my girlfriend and I left everything we have ever known behind in search of something better. We're still looking."
        }, 
        {
            "category": "Poetry", 
            "goal": "300.0", 
            "title": "WHAT! by Micah J Beck \u2014 Kickstarter", 
            "backers": "6", 
            "name": "Micah J Beck", 
            "currency": "USD", 
            "link": "https://www.kickstarter.com/projects/474392094/what/", 
            "location": "St. Louis, MO", 
            "totalPledged": "70.0", 
            "description": "\"What!\" is a collection of new poems written by Micah Beck"
        }
    ]
}