{
    "data": [
        {
            "category": "Webseries", 
            "goal": "27500.0", 
            "title": "\"I Never Met a Jerk I Didn't Like\" The Webseries by Jerry J White III \u2014 Kickstarter", 
            "backers": "31", 
            "name": "Jerry J White III", 
            "currency": "USD", 
            "link": "https://www.kickstarter.com/projects/35800211/i-never-met-a-jerk-i-didnt-like-the-webseries/", 
            "location": "North Hollywood, Los Angeles, CA", 
            "totalPledged": "1716.0", 
            "description": "We are making \"I Never Met a Jerk I Didn't Like\" into a webseries and need your help."
        }, 
        {
            "category": "Webseries", 
            "goal": "3581.0", 
            "title": "Math Warriors: Season 5 post-production (comedic webseries) by Kristina Harris \u2014 Kickstarter", 
            "backers": "46", 
            "name": "Kristina Harris", 
            "currency": "USD", 
            "link": "https://www.kickstarter.com/projects/2116354588/math-warriors-season-5-post-production-comedic-web/", 
            "location": "Manhattan, NY", 
            "totalPledged": "3585.0", 
            "description": "Love, betrayal...calculus.  The Funky Functions, a fictional college math team, strive to overcome seemingly insurmountable obstacles."
        }, 
        {
            "category": "Webseries", 
            "goal": "1000.0", 
            "title": "\"Cup of Love\" - Senior Thesis Web Series by Alyson Roseman \u2014 Kickstarter", 
            "backers": "57", 
            "name": "Alyson Roseman", 
            "currency": "USD", 
            "link": "https://www.kickstarter.com/projects/439834303/cup-of-love-senior-thesis-web-series/", 
            "location": "Syracuse, NY", 
            "totalPledged": "1690.3", 
            "description": "An idealistic barista sets up her customers based on their coffee orders in this quirky, comedic web series."
        }, 
        {
            "category": "Webseries", 
            "goal": "20000.0", 
            "title": "\"my roommate the..\" Kickstarter by my roommate the \u2014 Kickstarter", 
            "backers": "42", 
            "name": "my roommate the", 
            "currency": "USD", 
            "link": "https://www.kickstarter.com/projects/328006814/my-roommate-the-kickstarter/", 
            "location": "Los Angeles, CA", 
            "totalPledged": "2442.69", 
            "description": "Help \"my roommate the\" produce 2 epic episodes!And should we not reach our desired goal, your money will be kindly refunded :)"
        }, 
        {
            "category": "Webseries", 
            "goal": "30000.0", 
            "title": "ICUBALLING: Live youth Sports fundraising (HQ) by Paul Cannon \u2014 Kickstarter", 
            "backers": "6", 
            "name": "Paul Cannon", 
            "currency": "USD", 
            "link": "https://www.kickstarter.com/projects/2079274757/icuballing-live-high-school-sports-videos-hq/", 
            "location": "Laurel, MD", 
            "totalPledged": "460.0", 
            "description": "Youth sports are positive in so many ways to the community, players,and to the schools.  Building cyber stadiums help fund sports"
        }, 
        {
            "category": "Webseries", 
            "goal": "5500.0", 
            "title": "TYPE CAST : The Web Series by Celine Dayan-Bonilla + Brisa Freitas \u2014 Kickstarter", 
            "backers": "97", 
            "name": "Celine Dayan-Bonilla + Brisa Freitas", 
            "currency": "USD", 
            "link": "https://www.kickstarter.com/projects/3055864/type-cast-the-web-series/", 
            "location": "Astoria, Queens, NY", 
            "totalPledged": "5862.0", 
            "description": "Competing with your best friend for a lollipop is one thing. For your career, it's another..."
        }, 
        {
            "category": "Webseries", 
            "goal": "13375.0", 
            "title": "The Quotable Woman -- the webseries by Elaine Partnow \u2014 Kickstarter", 
            "backers": "188", 
            "name": "Elaine Partnow", 
            "currency": "USD", 
            "link": "https://www.kickstarter.com/projects/315576434/the-quotable-woman-the-webseries/", 
            "location": "Los Angeles, CA", 
            "totalPledged": "13901.0", 
            "description": "Living history portrayals of inspiring women in their own words, stunningly acted and filmed."
        }, 
        {
            "category": "Webseries", 
            "goal": "10000.0", 
            "title": "Ruthie's Bitchin' Kitchen by LindaCieslik, MarkHagen, C.Kocinski \u2014 Kickstarter", 
            "backers": "10", 
            "name": "LindaCieslik, MarkHagen, C.Kocinski", 
            "currency": "USD", 
            "link": "https://www.kickstarter.com/projects/1847249010/ruthies-bitchin-kitchen/", 
            "location": "Milwaukee, WI", 
            "totalPledged": "324.0", 
            "description": "Milwaukee's own Dear Ruthie cooks up a storm and shares bawdy commentary with sidekick Cynthia. Great recipes and lots of fun!"
        }, 
        {
            "category": "Webseries", 
            "goal": "12000.0", 
            "title": "Biking Into the World - Web Series by Harrison Brown \u2014 Kickstarter", 
            "backers": "367", 
            "name": "Harrison Brown", 
            "currency": "USD", 
            "link": "https://www.kickstarter.com/projects/408363530/biking-into-the-world-web-series/", 
            "location": "Hollywood, Los Angeles, CA", 
            "totalPledged": "12430.0", 
            "description": "Harrison Brown creates a real-time web series as he bikes over 6000 miles by himself from Alaska to Florida.  Join the adventure!"
        }, 
        {
            "category": "Webseries", 
            "goal": "8500.0", 
            "title": "-We need an app- so Kids see One Minute Gardener Videos- by One Minute Gardener \u2014 Kickstarter", 
            "backers": "4", 
            "name": "One Minute Gardener", 
            "currency": "USD", 
            "link": "https://www.kickstarter.com/projects/1740394362/we-need-an-app-so-kids-see-one-minute-gardener-vid/", 
            "location": "San Francisco, CA", 
            "totalPledged": "70.0", 
            "description": "~Kids can watch \"in a minute\" fun & educational videos for free.  ~Kids+Nature+Technology=Learn~Non-Profit Public Charity 501C3~"
        }, 
        {
            "category": "Webseries", 
            "goal": "1000.0", 
            "title": "Hipsters Anonymous: A Webseries by Katie Kawamoto \u2014 Kickstarter", 
            "backers": "42", 
            "name": "Katie Kawamoto", 
            "currency": "USD", 
            "link": "https://www.kickstarter.com/projects/186974978/hipsters-anonymous-a-webseries/", 
            "location": "Los Angeles, CA", 
            "totalPledged": "1381.0", 
            "description": "5 hipsters seek recovery from their addiction to hipsterism. #hipsterconfessions #hipstersanonymous #theycutoffthetrustfund"
        }, 
        {
            "category": "Webseries", 
            "goal": "10000.0", 
            "title": "A Finger Slip: Web Series by Naomi Javor \u2014 Kickstarter", 
            "backers": "601", 
            "name": "Naomi Javor", 
            "currency": "USD", 
            "link": "https://www.kickstarter.com/projects/1879289266/a-finger-slip-web-series/", 
            "location": "Suttons Bay, MI", 
            "totalPledged": "17386.45", 
            "description": "A webseries based on A Finger Slip by Pawtal (inspired by Sherlock Holmes) in which John and Sherlock accidentally meet through texts ."
        }, 
        {
            "category": "Webseries", 
            "goal": "1500.0", 
            "title": "The Ugly Friend Series Kickstarter by Dana Alyss (Stemrich) \u2014 Kickstarter", 
            "backers": "20", 
            "name": "Dana Alyss (Stemrich)", 
            "currency": "USD", 
            "link": "https://www.kickstarter.com/projects/181155166/the-ugly-friend-series-kickstarter/", 
            "location": "North Hollywood, Los Angeles, CA", 
            "totalPledged": "910.0", 
            "description": "Amanda Jenkins takes on her world, one ugly moment at a time."
        }, 
        {
            "category": "Webseries", 
            "goal": "8700.0", 
            "title": "59 Days in New York - A Musical Comedy for Online Audiences by May-Elise Martinsen \u2014 Kickstarter", 
            "backers": "71", 
            "name": "May-Elise Martinsen", 
            "currency": "USD", 
            "link": "https://www.kickstarter.com/projects/1024429439/59-days-in-new-york-a-musical-comedy-for-online-au/", 
            "location": "Brooklyn, NY", 
            "totalPledged": "13045.0", 
            "description": "59 Days in New York is a musical about tight budgets and big dreams. Watch our video to enjoy an original kickstarter song."
        }, 
        {
            "category": "Webseries", 
            "goal": "30000.0", 
            "title": "The Craziest Thing Webseries by Carolina Barbalace \u2014 Kickstarter", 
            "backers": "2", 
            "name": "Carolina Barbalace", 
            "currency": "USD", 
            "link": "https://www.kickstarter.com/projects/1357934225/the-craziest-thing-webseries/", 
            "location": "Northridge, Los Angeles, CA", 
            "totalPledged": "300.0", 
            "description": "We are not in this world alone. Follow this journey where people from all over the world answer one simple question..."
        }, 
        {
            "category": "Webseries", 
            "goal": "500.0", 
            "title": "The Jo March Vlog by Candace Kaw \u2014 Kickstarter", 
            "backers": "14", 
            "name": "Candace Kaw", 
            "currency": "USD", 
            "link": "https://www.kickstarter.com/projects/951021105/the-jo-march-vlog/", 
            "location": "Tampa, FL", 
            "totalPledged": "585.0", 
            "description": "A modern retelling of Little Women from Jo March's perspective."
        }, 
        {
            "category": "Webseries", 
            "goal": "15000.0", 
            "title": "Recalculating: Rediscovering the American Dream -Documentary by Nick Colicchio \u2014 Kickstarter", 
            "backers": "33", 
            "name": "Nick Colicchio", 
            "currency": "USD", 
            "link": "https://www.kickstarter.com/projects/1851565387/recalculating-rediscovering-the-american-dream-doc/", 
            "location": "Groton, MA", 
            "totalPledged": "4433.0", 
            "description": "Recalculating will be a documentary webseries about one 21 year old's experience traveling the country in search of The American Dream."
        }, 
        {
            "category": "Webseries", 
            "goal": "22500.0", 
            "title": "Disillusioned: The Series by Matt Marcy \u2014 Kickstarter", 
            "backers": "186", 
            "name": "Matt Marcy", 
            "currency": "USD", 
            "link": "https://www.kickstarter.com/projects/disillusioned/disillusioned-the-series/", 
            "location": "Los Angeles, CA", 
            "totalPledged": "22898.64", 
            "description": "A comedy web series about a professional magician struggling to find love, success, and respect in an art form that doesn't get any."
        }, 
        {
            "category": "Webseries", 
            "goal": "2500.0", 
            "title": "Battle of the AI the web series by Nicholas McKinney \u2014 Kickstarter", 
            "backers": "7", 
            "name": "Nicholas McKinney", 
            "currency": "USD", 
            "link": "https://www.kickstarter.com/projects/2brotherproductions/battle-of-the-ai-the-web-series/", 
            "location": "Gladewater, TX", 
            "totalPledged": "165.0", 
            "description": "We are two brothers that have an amazing story to tell.  We are wanting to create a web series called Battle of the AI's"
        }, 
        {
            "category": "Webseries", 
            "goal": "1000.0", 
            "title": "The In-Between Web Series by Whitley Porter \u2014 Kickstarter", 
            "backers": "5", 
            "name": "Whitley Porter", 
            "currency": "USD", 
            "link": "https://www.kickstarter.com/projects/395030433/the-in-between-web-series/", 
            "location": "San Bernardino, CA", 
            "totalPledged": "220.0", 
            "description": "The In-Between Web Series is a talk show designed to help millions of people discover their dreams and believe they can come true."
        }, 
        {
            "category": "Webseries", 
            "goal": "3370.0", 
            "title": "Nerd vs. Geek Season 1 DVD + New Episodes! by Stephanie Yuhas \u2014 Kickstarter", 
            "backers": "135", 
            "name": "Stephanie Yuhas", 
            "currency": "USD", 
            "link": "https://www.kickstarter.com/projects/stephanieyuhas/nerd-vs-geek-season-1-dvd/", 
            "location": "Philadelphia, PA", 
            "totalPledged": "4880.0", 
            "description": "A gamer circle, MENSA chapter, & drama club combine and clash as Craigslist roommates. Watch S1 on YouTube! Like it? Get a DVD!"
        }, 
        {
            "category": "Webseries", 
            "goal": "75000.0", 
            "title": "The Virtual Giant Walk-Through Brain by Drs. Lucy Brown & Helen Fisher \u2014 Kickstarter", 
            "backers": "145", 
            "name": "Drs. Lucy Brown & Helen Fisher", 
            "currency": "USD", 
            "link": "https://www.kickstarter.com/projects/339549328/the-virtual-giant-walk-through-brain/", 
            "location": "Bronx, NY", 
            "totalPledged": "75006.0", 
            "description": "Travel within an exciting human brain made for you, on the Internet. Play a game within love circuits..and learn how the brain works!"
        }, 
        {
            "category": "Webseries", 
            "goal": "2500.0", 
            "title": "Out Standing in the Field by Ileana Betancourt \u2014 Kickstarter", 
            "backers": "86", 
            "name": "Ileana Betancourt", 
            "currency": "USD", 
            "link": "https://www.kickstarter.com/projects/ileanab/out-standing-in-the-field/", 
            "location": "Ithaca, NY", 
            "totalPledged": "3052.0", 
            "description": "How can wearable technology like Google Glass influence our connection to the natural world? Let's find out!"
        }, 
        {
            "category": "Webseries", 
            "goal": "25000.0", 
            "title": "MONSTER GIRLS (working title) by Matt Soson \u2014 Kickstarter", 
            "backers": "485", 
            "name": "Matt Soson", 
            "currency": "USD", 
            "link": "https://www.kickstarter.com/projects/2102284932/monster-girls-working-title/", 
            "location": "Los Angeles, CA", 
            "totalPledged": "25681.0", 
            "description": "a new show about girls who bite..."
        }, 
        {
            "category": "Webseries", 
            "goal": "3000.0", 
            "title": "A New Sport Show For The New Generation of Sports Fans! by OTS - On The Sideline \u2014 Kickstarter", 
            "backers": "2", 
            "name": "OTS - On The Sideline", 
            "currency": "USD", 
            "link": "https://www.kickstarter.com/projects/1225535170/a-new-sport-show-for-the-new-generation-of-sports/", 
            "location": "Atlanta, GA", 
            "totalPledged": "30.0", 
            "description": "A Tad Bit of Comedy, Debates, and A Fresh New Look On Sports!"
        }, 
        {
            "category": "Webseries", 
            "goal": "9500.0", 
            "title": "John Martinez by Eric Espinosa \u2014 Kickstarter", 
            "backers": "0", 
            "name": "Eric Espinosa", 
            "currency": "USD", 
            "link": "https://www.kickstarter.com/projects/1180822098/john-martinez/", 
            "location": "New York, NY", 
            "totalPledged": "0.0", 
            "description": "We follow John and a handful of survivors as they search for their loved ones during a mysterious virus spreads thorughout the city."
        }, 
        {
            "category": "Webseries", 
            "goal": "2000.0", 
            "title": "City of Hope: Sex Trafficking (In Progress) by Alessandro Lopes \u2014 Kickstarter", 
            "backers": "1", 
            "name": "Alessandro Lopes", 
            "currency": "USD", 
            "link": "https://www.kickstarter.com/projects/pandaworks/city-of-hope-sex-trafficking-in-progress/", 
            "location": "New York, NY", 
            "totalPledged": "100.0", 
            "description": "A real story about a victim of sex trafficking and recreating it into a fiction series."
        }, 
        {
            "category": "Webseries", 
            "goal": "700.0", 
            "title": "Apolemigo Season 2 by Angelo Espiritu \u2014 Kickstarter", 
            "backers": "8", 
            "name": "Angelo Espiritu", 
            "currency": "USD", 
            "link": "https://www.kickstarter.com/projects/1707463700/apolemigo-season-2/", 
            "location": "Norfolk, VA", 
            "totalPledged": "270.0", 
            "description": "Apolemigo is a webseries by The Angelo Project that analyzes various social themes through sci-fi, mystery, and dramatic elements."
        }, 
        {
            "category": "Webseries", 
            "goal": "5000.0", 
            "title": "Down Out and Broke by Antwan McKelvin \u2014 Kickstarter", 
            "backers": "0", 
            "name": "Antwan McKelvin", 
            "currency": "USD", 
            "link": "https://www.kickstarter.com/projects/antwanmckelvin/down-out-and-broke/", 
            "location": "Los Angeles, CA", 
            "totalPledged": "0.0", 
            "description": "A new comedy about three guys making hard decision about career, friendship and life. Discovering new adventures, themselves and limits"
        }, 
        {
            "category": "Webseries", 
            "goal": "700.0", 
            "title": "Eternal Kingdom book trailer and promotion. by Josh Roger \u2014 Kickstarter", 
            "backers": "2", 
            "name": "Josh Roger", 
            "currency": "USD", 
            "link": "https://www.kickstarter.com/projects/166773474/eternal-kingdom-book-trailer-and-promotion/", 
            "location": "Detroit, MI", 
            "totalPledged": "30.0", 
            "description": "Eternal Kingdom is a classic good versus evil story delving into the multifaceted question, \"What is one person's life really worth?\""
        }, 
        {
            "category": "Webseries", 
            "goal": "5000.0", 
            "title": "Finding Adulthood by Fabio Ramon Meza \u2014 Kickstarter", 
            "backers": "13", 
            "name": "Fabio Ramon Meza", 
            "currency": "USD", 
            "link": "https://www.kickstarter.com/projects/6603337/finding-adulthood/", 
            "location": "Curitiba, Brazil", 
            "totalPledged": "575.0", 
            "description": "It isn't as bad as it sounds!A video series, blog, and community of millennials trying to figure life outwww.findingadulthood.com"
        }, 
        {
            "category": "Webseries", 
            "goal": "3200.0", 
            "title": "TROUBLESHOOTING: A comedic webseries by James Bianchi \u2014 Kickstarter", 
            "backers": "24", 
            "name": "James Bianchi", 
            "currency": "USD", 
            "link": "https://www.kickstarter.com/projects/1640651973/troubleshooting-a-comedic-webseries/", 
            "location": "West Hollywood, CA", 
            "totalPledged": "1217.0", 
            "description": "Jake is miserable. Huang is on the phone. A half-baked idea might just be enough to set them free. Time to start Troubleshooting."
        }, 
        {
            "category": "Webseries", 
            "goal": "50000.0", 
            "title": "devHour.tv - Movie-like Trailers for Restaurants by Tony Arce \u2014 Kickstarter", 
            "backers": "0", 
            "name": "Tony Arce", 
            "currency": "USD", 
            "link": "https://www.kickstarter.com/projects/tonyarce/devhourtv-movie-like-trailers-for-restaurants/", 
            "location": "Chicago, IL", 
            "totalPledged": "0.0", 
            "description": "Why dare to try the unknown? Preview restaurants with devHour.tv before you try them with restaurant trailers, produced in 1080p."
        }, 
        {
            "category": "Webseries", 
            "goal": "15000.0", 
            "title": "Portal: Secrets of Aperture - Webseries by Colin and Connor McGuire \u2014 Kickstarter", 
            "backers": "512", 
            "name": "Colin and Connor McGuire", 
            "currency": "USD", 
            "link": "https://www.kickstarter.com/projects/colinandconnor/portal-secrets-of-aperture-webseries/", 
            "location": "Pasadena, CA", 
            "totalPledged": "25022.34", 
            "description": "From the creators of Portal: Survive! comes a cinematic journey through the dark and secretive legacy of Aperture Science."
        }, 
        {
            "category": "Webseries", 
            "goal": "60000.0", 
            "title": "Peacekeepers by Charlie Reeves \u2014 Kickstarter", 
            "backers": "256", 
            "name": "Charlie Reeves", 
            "currency": "USD", 
            "link": "https://www.kickstarter.com/projects/949765334/peacekeepers/", 
            "location": "New York, NY", 
            "totalPledged": "30490.0", 
            "description": "One text ahead of the reaper: A new dark comedy that passes the Bechdel Test and echoes Buffy, Sherlock, & Doctor Who."
        }, 
        {
            "category": "Webseries", 
            "goal": "500.0", 
            "title": "High Quality 3DS Content! by King Gothalion \u2014 Kickstarter", 
            "backers": "14", 
            "name": "King Gothalion", 
            "currency": "USD", 
            "link": "https://www.kickstarter.com/projects/kinggothalion/high-quality-3ds-content/", 
            "location": "Tampa, FL", 
            "totalPledged": "537.0", 
            "description": "Hi There!As you may or may not know I have a Youtube/Twitch Channel! I am looking to expand and add 3DS content withy our help!"
        }, 
        {
            "category": "Webseries", 
            "goal": "10000.0", 
            "title": "Educating The Modern Man: Knowledge of previous generations by Modern Man Productions \u2014 Kickstarter", 
            "backers": "23", 
            "name": "Modern Man Productions", 
            "currency": "USD", 
            "link": "https://www.kickstarter.com/projects/1797546581/educating-the-modern-man-knowledge-of-previous-gen/", 
            "location": "Decatur, GA", 
            "totalPledged": "1551.0", 
            "description": "EMM is a Web Series/Documentary aimed at capturing the simple techniques that were so vital to everyone just a few short decades ago."
        }, 
        {
            "category": "Webseries", 
            "goal": "30000.0", 
            "title": "STILL : The Web Series by Jonathan Holbrook \u2014 Kickstarter", 
            "backers": "49", 
            "name": "Jonathan Holbrook", 
            "currency": "USD", 
            "link": "https://www.kickstarter.com/projects/1135497510/still-the-web-series/", 
            "location": "Everett, WA", 
            "totalPledged": "5213.0", 
            "description": "An unknown infection takes over a small Northwest town, SLOUGHTOWN, while a group of citizens attempt to escape to sanctuary."
        }, 
        {
            "category": "Webseries", 
            "goal": "22000.0", 
            "title": "Brian Remus: Science Genius by Unst Unst Unst Productions \u2014 Kickstarter", 
            "backers": "239", 
            "name": "Unst Unst Unst Productions", 
            "currency": "USD", 
            "link": "https://www.kickstarter.com/projects/lymanjohnson/brian-remus-science-genius/", 
            "location": "Los Angeles, CA", 
            "totalPledged": "25320.67", 
            "description": "A workplace comedy about a science show on a third-rate public broadcasting station."
        }, 
        {
            "category": "Webseries", 
            "goal": "6630.0", 
            "title": "Global Fusion Yoga: Exploring Yoga Across SE Asia and India by Mary Patton S. Davis \u2014 Kickstarter", 
            "backers": "53", 
            "name": "Mary Patton S. Davis", 
            "currency": "USD", 
            "link": "https://www.kickstarter.com/projects/1590137787/global-fusion-yoga-exploring-yoga-across-se-asia-a/", 
            "location": "Tampa, FL", 
            "totalPledged": "6940.0", 
            "description": "An online yoga video series highlighting regional styles and techniques. Take your yoga off the beaten mat!"
        }, 
        {
            "category": "Webseries", 
            "goal": "30000.0", 
            "title": "When Life Gives You Lemons by Don Barzegelli \u2014 Kickstarter", 
            "backers": "4", 
            "name": "Don Barzegelli", 
            "currency": "USD", 
            "link": "https://www.kickstarter.com/projects/1561809136/when-life-gives-you-lemons/", 
            "location": "Manassas, VA", 
            "totalPledged": "131.0", 
            "description": "This mockumentary shows ruthless leaders of a Drug Cartel selling narcotic-laced lemonade throughout a vicious Ring of Lemonade stands."
        }, 
        {
            "category": "Webseries", 
            "goal": "2000.0", 
            "title": "Roomsies Season 3 by Jenny and Meagan \u2014 Kickstarter", 
            "backers": "58", 
            "name": "Jenny and Meagan", 
            "currency": "USD", 
            "link": "https://www.kickstarter.com/projects/588680543/roomsies-season-3/", 
            "location": "New York, NY", 
            "totalPledged": "2155.0", 
            "description": "In Season 3 Jenny and Meagan will venture into the outside world and try to booty call some dudes without taking off their socks!"
        }, 
        {
            "category": "Webseries", 
            "goal": "3000.0", 
            "title": "Homestead or Dead. Wilderness, Survival, and the Internet. by Joseph Varner \u2014 Kickstarter", 
            "backers": "2", 
            "name": "Joseph Varner", 
            "currency": "USD", 
            "link": "https://www.kickstarter.com/projects/309588554/homestead-or-dead-wilderness-survival-and-the-inte/", 
            "location": "Mobile, AL", 
            "totalPledged": "2.0", 
            "description": "Ever wondered what you could do with only what you learned online and what you have lying around? Well lets find out!"
        }, 
        {
            "category": "Webseries", 
            "goal": "10000.0", 
            "title": "DON'T KILL ELI!  A Travel Show That YOU Control by Eli Newell \u2014 Kickstarter", 
            "backers": "192", 
            "name": "Eli Newell", 
            "currency": "USD", 
            "link": "https://www.kickstarter.com/projects/35472547/dont-kill-eli-a-travel-show-that-you-control/", 
            "location": "Los Angeles, CA", 
            "totalPledged": "14235.0", 
            "description": "Your votes send Host Eli Newell around the world in this Crowd-Sourced Travel Show. You can STILL be a backer! SEE BELOW!"
        }, 
        {
            "category": "Webseries", 
            "goal": "3500.0", 
            "title": "Sinner-Peace (Centerpiece) a DSLR film by Eddie Wright \u2014 Kickstarter", 
            "backers": "2", 
            "name": "Eddie Wright", 
            "currency": "USD", 
            "link": "https://www.kickstarter.com/projects/ifg/sinner-peace-centerpiece-a-dslr-film/", 
            "location": "Madison, MS", 
            "totalPledged": "10.0", 
            "description": "This web series will conquer love & labels. This series will be fun and emotional as it covers everyday issues in  relationship & life."
        }, 
        {
            "category": "Webseries", 
            "goal": "3000.0", 
            "title": "The Hollow Waltz Film Series by Steven Rand \u2014 Kickstarter", 
            "backers": "4", 
            "name": "Steven Rand", 
            "currency": "USD", 
            "link": "https://www.kickstarter.com/projects/steverstorm/the-hollow-waltz-film-series/", 
            "location": "Hartford, CT", 
            "totalPledged": "180.0", 
            "description": "4 part neo-noir film series about Colin, an art gallerist. He has limited time to make right on his past and plan for his bleak future"
        }, 
        {
            "category": "Webseries", 
            "goal": "5500.0", 
            "title": "Young Like Us: The Series by Young Like Us: The Series \u2014 Kickstarter", 
            "backers": "133", 
            "name": "Young Like Us: The Series", 
            "currency": "USD", 
            "link": "https://www.kickstarter.com/projects/2101090119/young-like-us-the-series/", 
            "location": "Brooklyn, NY", 
            "totalPledged": "8830.0", 
            "description": "Three ex-roommates start a fake band so they can stay real friends."
        }, 
        {
            "category": "Webseries", 
            "goal": "4000.0", 
            "title": "America's Next Top Chola by Vincent Amaya \u2014 Kickstarter", 
            "backers": "20", 
            "name": "Vincent Amaya", 
            "currency": "USD", 
            "link": "https://www.kickstarter.com/projects/vincentamaya/americas-next-top-chola/", 
            "location": "Los Angeles, CA", 
            "totalPledged": "4130.0", 
            "description": "9 Cholas compete to be America's Next Top Chola in this new scripted mockumentary series."
        }, 
        {
            "category": "Webseries", 
            "goal": "1000.0", 
            "title": "Let\u2019s make the world full of love! by Jin Young Kim \u2014 Kickstarter", 
            "backers": "1", 
            "name": "Jin Young Kim", 
            "currency": "USD", 
            "link": "https://www.kickstarter.com/projects/762664473/lets-make-the-world-full-of-love/", 
            "location": "Redmond, WA", 
            "totalPledged": "1.0", 
            "description": "We are not alone. You can say \"I love you\" to people in the world. And people will say \"I love you\" to you, too. (for iOS and Android)"
        }, 
        {
            "category": "Webseries", 
            "goal": "15000.0", 
            "title": "Online Permaculture Design Course with Scott Pittman by Christopher Badgett \u2014 Kickstarter", 
            "backers": "12", 
            "name": "Christopher Badgett", 
            "currency": "USD", 
            "link": "https://www.kickstarter.com/projects/340525589/online-permaculture-design-course-with-scott-pittm/", 
            "location": "Whitefish, MT", 
            "totalPledged": "2155.0", 
            "description": "Film a 2-week Permaculture Design Certificate Course in Costa Rica with Scott Pittman and create an online video course."
        }, 
        {
            "category": "Webseries", 
            "goal": "10000.0", 
            "title": "Natural 20s by Matthew Maitland \u2014 Kickstarter", 
            "backers": "24", 
            "name": "Matthew Maitland", 
            "currency": "USD", 
            "link": "https://www.kickstarter.com/projects/673308712/natural-20s/", 
            "location": "Nashville, TN", 
            "totalPledged": "1055.0", 
            "description": "Our story follows six D&D players who realize that relying on people is as necessary a skill in-game as it is out-of-game."
        }, 
        {
            "category": "Webseries", 
            "goal": "200000.0", 
            "title": "World and Life Travels by Chad Beaty \u2014 Kickstarter", 
            "backers": "0", 
            "name": "Chad Beaty", 
            "currency": "USD", 
            "link": "https://www.kickstarter.com/projects/115484722/world-and-life-travels/", 
            "location": "Leesburg, VA", 
            "totalPledged": "0.0", 
            "description": "Traveling world web series, free to all on youtube. With a very nice Life and world travels website. From Europe to Asia and more."
        }, 
        {
            "category": "Webseries", 
            "goal": "3100.0", 
            "title": "Every Point on the Map by Kelly Roberts \u2014 Kickstarter", 
            "backers": "42", 
            "name": "Kelly Roberts", 
            "currency": "USD", 
            "link": "https://www.kickstarter.com/projects/523514303/every-point-on-the-map/", 
            "location": "Edmond, OK", 
            "totalPledged": "3166.0", 
            "description": "A multi-media, cultural quest to complete a meaningful conversation with one person at each of the 593 points on State of Oklahoma map."
        }, 
        {
            "category": "Webseries", 
            "goal": "7500.0", 
            "title": "Super Fun Show, with Learning! Episode 2 by Lexie Kahanovitz \u2014 Kickstarter", 
            "backers": "192", 
            "name": "Lexie Kahanovitz", 
            "currency": "USD", 
            "link": "https://www.kickstarter.com/projects/1470824776/super-fun-show-with-learning-episode-2/", 
            "location": "New York, NY", 
            "totalPledged": "7832.55", 
            "description": "A sci-fi kids show for adults that journeys inside the internet in a Tron meets Reading Rainbow adventure."
        }, 
        {
            "category": "Webseries", 
            "goal": "10000.0", 
            "title": "Co-Husbands: A New Kind of Family Sitcom by Devin Sullivan \u2014 Kickstarter", 
            "backers": "96", 
            "name": "Devin Sullivan", 
            "currency": "USD", 
            "link": "https://www.kickstarter.com/projects/1888501324/co-husbands-a-new-kind-of-family-sitcom/", 
            "location": "Los Angeles, CA", 
            "totalPledged": "11050.01", 
            "description": "Co-Husbands is an ensemble comedy-series about one woman and her three husbands."
        }, 
        {
            "category": "Webseries", 
            "goal": "13500.0", 
            "title": "A Perfect Situation by Ryan MacDonald \u2014 Kickstarter", 
            "backers": "60", 
            "name": "Ryan MacDonald", 
            "currency": "USD", 
            "link": "https://www.kickstarter.com/projects/1020091542/a-perfect-situation/", 
            "location": "Springfield, PA", 
            "totalPledged": "13694.0", 
            "description": "What would actually happen if your best friend actually ran out of her wedding to be with you?"
        }, 
        {
            "category": "Webseries", 
            "goal": "600.0", 
            "title": "Cueboy by Hox-z Productions \u2014 Kickstarter", 
            "backers": "19", 
            "name": "Hox-z Productions", 
            "currency": "USD", 
            "link": "https://www.kickstarter.com/projects/978639638/cueboy/", 
            "location": "Syracuse, NY", 
            "totalPledged": "605.0", 
            "description": "An original superhero known as Cueboy protects the city of Poolville with help from Secret Government Agent Pete Rack."
        }, 
        {
            "category": "Webseries", 
            "goal": "6000.0", 
            "title": "Sunday Brunch The Series by Nicola Graham, Kelsey Law, Sara Lohman \u2014 Kickstarter", 
            "backers": "159", 
            "name": "Nicola Graham, Kelsey Law, Sara Lohman", 
            "currency": "USD", 
            "link": "https://www.kickstarter.com/projects/935996538/sunday-brunch-the-series/", 
            "location": "Los Angeles, CA", 
            "totalPledged": "7910.69", 
            "description": "A wry comedy that delves into the lives of 3 girlfriends conquering LA...with the help of a lot of cocktails.  Sunday Bloody Sunday."
        }, 
        {
            "category": "Webseries", 
            "goal": "5000.0", 
            "title": "Kamakazshow Alternative Sketch Comedy Show by N. M. Howe \u2014 Kickstarter", 
            "backers": "17", 
            "name": "N. M. Howe", 
            "currency": "USD", 
            "link": "https://www.kickstarter.com/projects/1675850855/kamakazshow-alternative-sketch-comedy-show/", 
            "location": "Tulsa, OK", 
            "totalPledged": "5202.01", 
            "description": "At Howe Productions, sketch comedy runs in our veins and our series for this upcoming already written season needs a kickstart."
        }, 
        {
            "category": "Webseries", 
            "goal": "5000.0", 
            "title": "The Hernandez Factor: Transformative Regression by Dr. Michelle Hernandez \u2014 Kickstarter", 
            "backers": "5", 
            "name": "Dr. Michelle Hernandez", 
            "currency": "USD", 
            "link": "https://www.kickstarter.com/projects/thf/the-hernandez-factor-transformative-regression/", 
            "location": "San Francisco, CA", 
            "totalPledged": "475.0", 
            "description": "Two women with juvenile rheumatoid arthritis undergo a transformative event."
        }, 
        {
            "category": "Webseries", 
            "goal": "4000.0", 
            "title": "The Employment of Aren Blackly by Robert David Foster \u2014 Kickstarter", 
            "backers": "10", 
            "name": "Robert David Foster", 
            "currency": "USD", 
            "link": "https://www.kickstarter.com/projects/667412499/the-employment-of-aren-blackly/", 
            "location": "St. Joseph, MI", 
            "totalPledged": "486.0", 
            "description": "In this action drama web series, Aren Blackly is a half angel half demon, who must overcome great peril and moral challenges."
        }, 
        {
            "category": "Webseries", 
            "goal": "3000.0", 
            "title": "Buddy The Puca: Season 1 by Dennis Tammany \u2014 Kickstarter", 
            "backers": "10", 
            "name": "Dennis Tammany", 
            "currency": "USD", 
            "link": "https://www.kickstarter.com/projects/1415004298/buddy-the-puca-season-1/", 
            "location": "Phoenixville, PA", 
            "totalPledged": "600.0", 
            "description": "Buddy the Puca is the tale of Jimmy, a timid and down on his luck guy, who has been both befriended & tormented by a Puca named Buddy."
        }, 
        {
            "category": "Webseries", 
            "goal": "2475.0", 
            "title": "The Drunk Whisperer by AndLew Entertainment \u2014 Kickstarter", 
            "backers": "52", 
            "name": "AndLew Entertainment", 
            "currency": "USD", 
            "link": "https://www.kickstarter.com/projects/731224660/the-drunk-whisperer/", 
            "location": "Hollywood, Los Angeles, CA", 
            "totalPledged": "2605.0", 
            "description": "AndLew Entertainment and Kevin Comartin present: THE DRUNK WHISPERER with Christopher Millan"
        }, 
        {
            "category": "Webseries", 
            "goal": "902.0", 
            "title": "Theta - A Non-Profit Sci-Fi Webseries by Kurt and Nadia Peterson \u2014 Kickstarter", 
            "backers": "71", 
            "name": "Kurt and Nadia Peterson", 
            "currency": "USD", 
            "link": "https://www.kickstarter.com/projects/1913012135/theta-a-non-profit-sci-fi-webseries/", 
            "location": "Denver, CO", 
            "totalPledged": "2321.0", 
            "description": "A webseries following a humble team tasked with protecting the last of humanity from the terrors of an uncharted world."
        }, 
        {
            "category": "Webseries", 
            "goal": "65000.0", 
            "title": "BROTHERHOOD CODE OF THE STREETZ by Cory Thompson and Edward Jones \u2014 Kickstarter", 
            "backers": "9", 
            "name": "Cory Thompson and Edward Jones", 
            "currency": "USD", 
            "link": "https://www.kickstarter.com/projects/brotherhoodcots/brotherhood-code-of-the-streetz/", 
            "location": "New York, NY", 
            "totalPledged": "5705.0", 
            "description": "A Gut-Wrenching, Riveting, Dynamic Must See Urban Web Series based on True-Life Events."
        }, 
        {
            "category": "Webseries", 
            "goal": "2750.0", 
            "title": "Dare to Truth Webseries by Daniel Knox (deleted) \u2014 Kickstarter", 
            "backers": "0", 
            "name": "Daniel Knox (deleted)", 
            "currency": "USD", 
            "link": "https://www.kickstarter.com/projects/318965064/dare-to-truth-series/", 
            "location": "Danielson, CT", 
            "totalPledged": "0.0", 
            "description": "This Kickstarter is to make an interactive webseries based on the games like truth or dare. Suggestions for games come from viewers."
        }, 
        {
            "category": "Webseries", 
            "goal": "15000.0", 
            "title": "GAYLE Season Three by Chris Fleming \u2014 Kickstarter", 
            "backers": "498", 
            "name": "Chris Fleming", 
            "currency": "USD", 
            "link": "https://www.kickstarter.com/projects/chrisflemingfleming/gayle-season-three/", 
            "location": "Los Angeles, CA", 
            "totalPledged": "15516.71", 
            "description": "A webseries about a strong suburban woman named Gayle Waters-Waters."
        }, 
        {
            "category": "Webseries", 
            "goal": "25000.0", 
            "title": "THRONE: RMC by CD Newton \u2014 Kickstarter", 
            "backers": "0", 
            "name": "CD Newton", 
            "currency": "USD", 
            "link": "https://www.kickstarter.com/projects/throne/throne-rmc/", 
            "location": "Cleveland, OH", 
            "totalPledged": "0.0", 
            "description": "THRONE is Coming to America 2 on steroids! 'Zoomoonda' is in crisis. Besieged by scandal, murder and a power struggle. King vs General!"
        }, 
        {
            "category": "Webseries", 
            "goal": "2200.0", 
            "title": "Lunes (Season 1) - A YouTube-based Webseries by Sky Maldonado \u2014 Kickstarter", 
            "backers": "2", 
            "name": "Sky Maldonado", 
            "currency": "USD", 
            "link": "https://www.kickstarter.com/projects/1791954666/lunes-season-1-a-youtube-based-webseries/", 
            "location": "Seattle, WA", 
            "totalPledged": "210.0", 
            "description": "Lunes will be a dark, supernatural, 6-episode web series streamed weekly on YouTube. Episodes will be short, but high quality."
        }, 
        {
            "category": "Webseries", 
            "goal": "16850.0", 
            "title": "Scoots of Anarchy: The Mini-Series by West Waters Productions \u2014 Kickstarter", 
            "backers": "68", 
            "name": "West Waters Productions", 
            "currency": "USD", 
            "link": "https://www.kickstarter.com/projects/1392064417/scoots-of-anarchy-the-mini-series/", 
            "location": "Los Angeles, CA", 
            "totalPledged": "3283.0", 
            "description": "Ride with Scoots on their epic adventures as they not only spoof Sons of Anarchy, but other popular film and Television as well!"
        }, 
        {
            "category": "Webseries", 
            "goal": "30000.0", 
            "title": "New Beginnings! - Korey Coleman's new website project! by Korey Coleman \u2014 Kickstarter", 
            "backers": "2,424", 
            "name": "Korey Coleman", 
            "currency": "USD", 
            "link": "https://www.kickstarter.com/projects/573779592/it-aint-going-down-like-that-korey-colemans-new-si/", 
            "location": "Austin, TX", 
            "totalPledged": "133860.8", 
            "description": "Over the years we've created great content and a great community. Now I'm on my own, and I want to recreate that experience for you."
        }, 
        {
            "category": "Webseries", 
            "goal": "25000.0", 
            "title": "Amazon Rage: Curse of the She-Wolf (Pre-Production) by Exiram Productions \u2014 Kickstarter", 
            "backers": "0", 
            "name": "Exiram Productions", 
            "currency": "USD", 
            "link": "https://www.kickstarter.com/projects/exiram/amazon-rage-curse-of-the-she-wolf-pre-production/", 
            "location": "New York, NY", 
            "totalPledged": "0.0", 
            "description": "Amazon Werewolves from Outer Space"
        }, 
        {
            "category": "Webseries", 
            "goal": "15687.0", 
            "title": "The Organization 5 by Mr. Hand \u2014 Kickstarter", 
            "backers": "0", 
            "name": "Mr. Hand", 
            "currency": "USD", 
            "link": "https://www.kickstarter.com/projects/821241184/the-organization-5/", 
            "location": "Buffalo, NY", 
            "totalPledged": "0.0", 
            "description": "Enter the Organization 5, where super villain hand puppets (and an evil piggie bank) scheme to take over the world...without success."
        }, 
        {
            "category": "Webseries", 
            "goal": "10000.0", 
            "title": "The  Majestics by The Majestics Cast & Crew \u2014 Kickstarter", 
            "backers": "54", 
            "name": "The Majestics Cast & Crew", 
            "currency": "USD", 
            "link": "https://www.kickstarter.com/projects/1320641757/the-majestics/", 
            "location": "North Hollywood, Los Angeles, CA", 
            "totalPledged": "6607.0", 
            "description": "A comedic look at 5 siblings thrown together under one roof by the death of their mother and how they become a family."
        }, 
        {
            "category": "Webseries", 
            "goal": "5000.0", 
            "title": "How Come I'm Not Famous Yet?- Independent Pilot Project by Katherine Weatherford & Nick Pearson \u2014 Kickstarter", 
            "backers": "88", 
            "name": "Katherine Weatherford & Nick Pearson", 
            "currency": "USD", 
            "link": "https://www.kickstarter.com/projects/1726230179/how-come-im-not-famous-yet-independent-pilot-proje/", 
            "location": "New York, NY", 
            "totalPledged": "5926.0", 
            "description": "Got a dream?  Us too!  Not there yet?  Us too!!  And we wrote a show about it.  The journey to get there is the most entertaining part!"
        }, 
        {
            "category": "Webseries", 
            "goal": "27000.0", 
            "title": "Biking Dawn by Dan Stebbins \u2014 Kickstarter", 
            "backers": "53", 
            "name": "Dan Stebbins", 
            "currency": "USD", 
            "link": "https://www.kickstarter.com/projects/danstebbins/biking-dawn-season-one/", 
            "location": "Brooklyn, NY", 
            "totalPledged": "2517.0", 
            "description": "A bicycle-centric action / comedy series taking a stand against the disastrous effects of automobiles."
        }, 
        {
            "category": "Webseries", 
            "goal": "1850.0", 
            "title": "\"I Heart L.A.: Where No Good Deed Goes Unpunished\" by I Heart L.A. Productions \u2014 Kickstarter", 
            "backers": "6", 
            "name": "I Heart L.A. Productions", 
            "currency": "USD", 
            "link": "https://www.kickstarter.com/projects/1158397974/i-heart-la-where-no-good-deed-goes-unpunished/", 
            "location": "Glendale, CA", 
            "totalPledged": "71.0", 
            "description": "\"Seinfeld\" in L.A. ... but with an actor! Think \"Seinfeld\" meets \"Friends\" on the mean streets of Los Angeles."
        }, 
        {
            "category": "Webseries", 
            "goal": "30000.0", 
            "title": "The Flip Side, Web Series by sam pezzullo \u2014 Kickstarter", 
            "backers": "2", 
            "name": "sam pezzullo", 
            "currency": "USD", 
            "link": "https://www.kickstarter.com/projects/sampezzullo/the-flip-side-web-series/", 
            "location": "New York, NY", 
            "totalPledged": "35.0", 
            "description": "5 years in the making; the reality show that could have been gets its second chance as a web-series. Stay tuned."
        }, 
        {
            "category": "Webseries", 
            "goal": "6000.0", 
            "title": "Small Stage:  an original web series by Amanda Jeronimus \u2014 Kickstarter", 
            "backers": "57", 
            "name": "Amanda Jeronimus", 
            "currency": "USD", 
            "link": "https://www.kickstarter.com/projects/1752432142/small-stage-an-original-web-series/", 
            "location": "Minneapolis, MN", 
            "totalPledged": "6930.0", 
            "description": "A web series that reveals the fantasy and mystery hidden in one small Midwestern town."
        }, 
        {
            "category": "Webseries", 
            "goal": "10000.0", 
            "title": "The DeadEnders by Single Schred Productions \u2014 Kickstarter", 
            "backers": "15", 
            "name": "Single Schred Productions", 
            "currency": "USD", 
            "link": "https://www.kickstarter.com/projects/thedeadenders/the-deadenders/", 
            "location": "Tacoma, WA", 
            "totalPledged": "951.4", 
            "description": "This is a story about a group surviving against all odds, learning to work as a team in an attempt to eradicate the world of Zombies !!"
        }, 
        {
            "category": "Webseries", 
            "goal": "1500.0", 
            "title": "Willy's Cocina:  Cooking with Family by William \u2014 Kickstarter", 
            "backers": "4", 
            "name": "William", 
            "currency": "USD", 
            "link": "https://www.kickstarter.com/projects/1959912841/willys-cocina-cooking-with-family/", 
            "location": "Oklahoma City, OK", 
            "totalPledged": "70.0", 
            "description": "A web-series cooking show that brings together local businesses and people to share their family stories and recipes."
        }, 
        {
            "category": "Webseries", 
            "goal": "800.0", 
            "title": "MstSage Entertainment Website by Rane MstSage \u2014 Kickstarter", 
            "backers": "0", 
            "name": "Rane MstSage", 
            "currency": "USD", 
            "link": "https://www.kickstarter.com/projects/1698668350/mstsage-entertainment-website/", 
            "location": "Lennon, MI", 
            "totalPledged": "0.0", 
            "description": "Entertainment and Gaming website, with fun Let's Plays and Roll The Bones!"
        }, 
        {
            "category": "Webseries", 
            "goal": "3000.0", 
            "title": "Girls Game Too! by Katie Henderson \u2014 Kickstarter", 
            "backers": "10", 
            "name": "Katie Henderson", 
            "currency": "USD", 
            "link": "https://www.kickstarter.com/projects/1740228178/girls-game-too/", 
            "location": "Little Elm, TX", 
            "totalPledged": "210.0", 
            "description": "Girls game too, and I'm going to webcast our adventures!"
        }, 
        {
            "category": "Webseries", 
            "goal": "35000.0", 
            "title": "History Hunter DVD Series by Richie Castro \u2014 Kickstarter", 
            "backers": "73", 
            "name": "Richie Castro", 
            "currency": "USD", 
            "link": "https://www.kickstarter.com/projects/91141976/history-hunter-dvd-series/", 
            "location": "Denver, CO", 
            "totalPledged": "9780.0", 
            "description": "History Hunter is a 'edu-tainement' program that teaches world history through music, storytelling and theatrics."
        }, 
        {
            "category": "Webseries", 
            "goal": "4200.0", 
            "title": "The Cool Kids by Zach Rice \u2014 Kickstarter", 
            "backers": "34", 
            "name": "Zach Rice", 
            "currency": "USD", 
            "link": "https://www.kickstarter.com/projects/565732732/the-cool-kids/", 
            "location": "Orange, CA", 
            "totalPledged": "4786.0", 
            "description": "With incredibly dark humor, this hilarious and uncensored web-series shines a whole new light on the insanity of high school."
        }, 
        {
            "category": "Webseries", 
            "goal": "5500.0", 
            "title": "Pursuit of the Unknown Shredder by Brian Orne \u2014 Kickstarter", 
            "backers": "16", 
            "name": "Brian Orne", 
            "currency": "USD", 
            "link": "https://www.kickstarter.com/projects/1384512873/pursuit-of-the-unknown-shredder/", 
            "location": "Marblehead, MA", 
            "totalPledged": "595.0", 
            "description": "A 4 month long 8 episode webseries exploring North America's great west in pursuit of the Unknown Shredder"
        }, 
        {
            "category": "Webseries", 
            "goal": "7500.0", 
            "title": "Zombie Smarts! by Robert Whitehead Ray Hosack \u2014 Kickstarter", 
            "backers": "4", 
            "name": "Robert Whitehead Ray Hosack", 
            "currency": "USD", 
            "link": "https://www.kickstarter.com/projects/315299330/zombie-smarts/", 
            "location": "Plano, TX", 
            "totalPledged": "90.0", 
            "description": "A short web series describing the origin, evolution, changes and challenges of social media marketing."
        }, 
        {
            "category": "Webseries", 
            "goal": "85000.0", 
            "title": "From the Ground Up by Keith Waters \u2014 Kickstarter", 
            "backers": "3", 
            "name": "Keith Waters", 
            "currency": "USD", 
            "link": "https://www.kickstarter.com/projects/keithwaters/from-the-ground-up-3/", 
            "location": "Stuart, FL", 
            "totalPledged": "115.0", 
            "description": "The Web Series about making a Web Series ... \"From the Ground Up\"."
        }, 
        {
            "category": "Webseries", 
            "goal": "8717.0", 
            "title": "Pearly Gates by Bo Belanger \u2014 Kickstarter", 
            "backers": "161", 
            "name": "Bo Belanger", 
            "currency": "USD", 
            "link": "https://www.kickstarter.com/projects/735873055/pearly-gates/", 
            "location": "Los Angeles, CA", 
            "totalPledged": "11250.0", 
            "description": "A show about Jesus and his famous friends in Heaven... except since they've already made it into Heaven, no one acts good anymore."
        }, 
        {
            "category": "Webseries", 
            "goal": "200000.0", 
            "title": "Going for Gold Production - Season 1 Figure Skating Edition by Bryce Johnson, Executive Producer \u2014 Kickstarter", 
            "backers": "4", 
            "name": "Bryce Johnson, Executive Producer", 
            "currency": "USD", 
            "link": "https://www.kickstarter.com/projects/304832638/going-for-gold-production-season-1-figure-skating/", 
            "location": "Salt Lake City, UT", 
            "totalPledged": "155.0", 
            "description": "Capturing stories of endurance to inspire you to pursue your own goals. \"Todays Hopefuls, Tomorrows Champions\""
        }, 
        {
            "category": "Webseries", 
            "goal": "10000.0", 
            "title": "SLAGMARKER by Kyle Kerlan \u2014 Kickstarter", 
            "backers": "6", 
            "name": "Kyle Kerlan", 
            "currency": "USD", 
            "link": "https://www.kickstarter.com/projects/74962245/slagmarker/", 
            "location": "San Francisco, CA", 
            "totalPledged": "766.0", 
            "description": "A reality web series where everyday people are thrust into a fantasy world of unscripted gladiatorial combat."
        }, 
        {
            "category": "Webseries", 
            "goal": "10000.0", 
            "title": "Tinker Steampunk Web Series by Containment Field Studio \u2014 Kickstarter", 
            "backers": "240", 
            "name": "Containment Field Studio", 
            "currency": "USD", 
            "link": "https://www.kickstarter.com/projects/containmentfield/tinker-steampunk-web-series/", 
            "location": "Los Angeles, CA", 
            "totalPledged": "13045.6", 
            "description": "Escape with us to a sci-fi world where a pair of genius inventors battle villains to bring change to a polluted & corrupt world."
        }, 
        {
            "category": "Webseries", 
            "goal": "10000.0", 
            "title": "Pairings Season 2 by Ed Robinson \u2014 Kickstarter", 
            "backers": "116", 
            "name": "Ed Robinson", 
            "currency": "USD", 
            "link": "https://www.kickstarter.com/projects/pairingsed/pairings-season-2", 
            "location": "North Hollywood, Los Angeles, CA", 
            "totalPledged": "10097.0", 
            "description": "Season 2 of the award winning series. Can Alan learn to balance his love life as well as he does flavors in a dish?"
        }, 
        {
            "category": "Webseries", 
            "goal": "1672000.0", 
            "title": "Tribes of the CaveFan by Thomas Foster \u2014 Kickstarter", 
            "backers": "3", 
            "name": "Thomas Foster", 
            "currency": "USD", 
            "link": "https://www.kickstarter.com/projects/1570541207/tribes-of-the-cavefan/", 
            "location": "Davis, CA", 
            "totalPledged": "7.0", 
            "description": "\u201cTribes of the CaveFan\u201dwill be an interior design show with a nerdy twist.  The team will create a fandom cave dedicated to the client."
        }, 
        {
            "category": "Webseries", 
            "goal": "500.0", 
            "title": "Wasteland by Matt Mudd \u2014 Kickstarter", 
            "backers": "1", 
            "name": "Matt Mudd", 
            "currency": "USD", 
            "link": "https://www.kickstarter.com/projects/903407179/wasteland/", 
            "location": "Nampa, ID", 
            "totalPledged": "50.0", 
            "description": "In the Apocalypse, he who owns the key to survival, has the power."
        }, 
        {
            "category": "Webseries", 
            "goal": "50000.0", 
            "title": "Elaysia - The Webseries by Deidre Greenfield \u2014 Kickstarter", 
            "backers": "2", 
            "name": "Deidre Greenfield", 
            "currency": "USD", 
            "link": "https://www.kickstarter.com/projects/1257550522/elaysia-a-long-term-video-project/", 
            "location": "Bellevue, WA", 
            "totalPledged": "127.0", 
            "description": "When war ravages a far away land, elves, humans and dwarves alike must unite to take down a bigger enemy."
        }, 
        {
            "category": "Webseries", 
            "goal": "1820.0", 
            "title": "Help a Growing YouTube Fashion/Lifestyle Channel! by Gil Ribero \u2014 Kickstarter", 
            "backers": "0", 
            "name": "Gil Ribero", 
            "currency": "USD", 
            "link": "https://www.kickstarter.com/projects/2082695982/help-a-growing-youtube-fashion-lifestyle-channel/", 
            "location": "Los Angeles, CA", 
            "totalPledged": "0.0", 
            "description": "Please join this collaborative effort to improve my entrepreneur daughter's YouTube channel quality and overall appeal. Thank you!"
        }, 
        {
            "category": "Webseries", 
            "goal": "30000.0", 
            "title": "MAX EATS PEOPLE by Radacity Productions \u2014 Kickstarter", 
            "backers": "1", 
            "name": "Radacity Productions", 
            "currency": "USD", 
            "link": "https://www.kickstarter.com/projects/48558732/max-eats-people/", 
            "location": "Atlanta, GA", 
            "totalPledged": "1.0", 
            "description": "An innovative comedy/horror web series starring Max, your friendly neighborhood cannibal!"
        }, 
        {
            "category": "Webseries", 
            "goal": "5000.0", 
            "title": "Menchildren of McHenry (pilot) by Menchildren of McHenry \u2014 Kickstarter", 
            "backers": "116", 
            "name": "Menchildren of McHenry", 
            "currency": "USD", 
            "link": "https://www.kickstarter.com/projects/1848870906/menchildren-of-mchenry-pilot/", 
            "location": "Mchenry, IL", 
            "totalPledged": "5215.0", 
            "description": "A comedy webseries chronicling the misadventures of a group of friends living in a seemingly unremarkable town in midwest suburbia."
        }, 
        {
            "category": "Webseries", 
            "goal": "35000.0", 
            "title": "The Kindness Effect by Blue Truck TV (deleted) \u2014 Kickstarter", 
            "backers": "34", 
            "name": "Blue Truck TV (deleted)", 
            "currency": "USD", 
            "link": "https://www.kickstarter.com/projects/thekindnesseffect/the-kindness-effect/", 
            "location": "Fort Lauderdale, FL", 
            "totalPledged": "3558.0", 
            "description": "An inspiring and hysterical, hidden-camera reality show with a unique twist. Instead of practical jokes, we \"prank\" people for good!"
        }, 
        {
            "category": "Webseries", 
            "goal": "10000.0", 
            "title": "STUCK - The Web Series by STUCK \u2014 Kickstarter", 
            "backers": "61", 
            "name": "STUCK", 
            "currency": "USD", 
            "link": "https://www.kickstarter.com/projects/177414458/stuck-the-web-series/", 
            "location": "Atlanta, GA", 
            "totalPledged": "5448.0", 
            "description": "A new series that follows the lives of townies in a community where unemployment is nothing new.... Drunks, Sex fiends, & Drop-Outs!"
        }, 
        {
            "category": "Webseries", 
            "goal": "5500.0", 
            "title": "Pilot Episode \"Out of Your Element\" by Janee Hayes \u2014 Kickstarter", 
            "backers": "42", 
            "name": "Janee Hayes", 
            "currency": "USD", 
            "link": "https://www.kickstarter.com/projects/1298731888/pilot-episode-out-of-your-element/", 
            "location": "Washington, DC", 
            "totalPledged": "5660.0", 
            "description": "It's one thing to see stars excel in their areas of expertise, but what happens when they are placed in totally unfamiliar situations?"
        }, 
        {
            "category": "Webseries", 
            "goal": "3000.0", 
            "title": "Just Like You by Isaiah Wilson \u2014 Kickstarter", 
            "backers": "6", 
            "name": "Isaiah Wilson", 
            "currency": "USD", 
            "link": "https://www.kickstarter.com/projects/7050352/just-like-you/", 
            "location": "Cocoa, FL", 
            "totalPledged": "46.0", 
            "description": "A show about being gay, straight, black, white, male, female, transgendered, Christian, Atheist and everything inbetween."
        }, 
        {
            "category": "Webseries", 
            "goal": "2000.0", 
            "title": "Reaction News by Isaac Mead-Long \u2014 Kickstarter", 
            "backers": "6", 
            "name": "Isaac Mead-Long", 
            "currency": "USD", 
            "link": "https://www.kickstarter.com/projects/453229927/reaction-news/", 
            "location": "Miami, FL", 
            "totalPledged": "395.0", 
            "description": "Rich Sanchez is a reporter with one mission. To catch Florida Man! An elusive criminal mastermind terrorizing Florida."
        }, 
        {
            "category": "Webseries", 
            "goal": "500.0", 
            "title": "The City Of Hope: Sex Trafficking by Alessandro Lopes \u2014 Kickstarter", 
            "backers": "19", 
            "name": "Alessandro Lopes", 
            "currency": "USD", 
            "link": "https://www.kickstarter.com/projects/pandaworks/the-city-of-hope/", 
            "location": "New York, NY", 
            "totalPledged": "786.0", 
            "description": "Real life sex trafficking stories and recreating them into fictional web-series."
        }, 
        {
            "category": "Webseries", 
            "goal": "1100.0", 
            "title": "Glass in the Class by Michael Cherin \u2014 Kickstarter", 
            "backers": "6", 
            "name": "Michael Cherin", 
            "currency": "USD", 
            "link": "https://www.kickstarter.com/projects/636779635/glass-in-the-class/", 
            "location": "Los Angeles, CA", 
            "totalPledged": "51.0", 
            "description": "An original weekly webisode about how Google Glass will revolutionize learning."
        }, 
        {
            "category": "Webseries", 
            "goal": "8000.0", 
            "title": "The Heartless Webseries by Brandon Doo \u2014 Kickstarter", 
            "backers": "14", 
            "name": "Brandon Doo", 
            "currency": "USD", 
            "link": "https://www.kickstarter.com/projects/1165169510/the-heartless-webseries/", 
            "location": "Glendale, CA", 
            "totalPledged": "633.0", 
            "description": "The Heartless is a new webseries about a man traveling through the zombie infested wasteland of civilization."
        }, 
        {
            "category": "Webseries", 
            "goal": "6000.0", 
            "title": "Bite Sized by Bite Sized \u2014 Kickstarter", 
            "backers": "79", 
            "name": "Bite Sized", 
            "currency": "USD", 
            "link": "https://www.kickstarter.com/projects/1078516757/bite-sized/", 
            "location": "Los Angeles, CA", 
            "totalPledged": "6081.0", 
            "description": "Life happens around food. This is a show about that. We're simple and kind of sassy. Help us fund Season 2!"
        }, 
        {
            "category": "Webseries", 
            "goal": "11000.0", 
            "title": "Front of House - A Web Series by Stefanie Williams (deleted) \u2014 Kickstarter", 
            "backers": "64", 
            "name": "Stefanie Williams (deleted)", 
            "currency": "USD", 
            "link": "https://www.kickstarter.com/projects/1599633119/front-of-house-a-web-series/", 
            "location": "New York, NY", 
            "totalPledged": "11200.55", 
            "description": "Front of House is a scripted web series about three friends and their different lives and experiences working in a restaurant in NYC."
        }, 
        {
            "category": "Webseries", 
            "goal": "1000.0", 
            "title": "Motivating Greatness Revolution by Chad Gaytan \u2014 Kickstarter", 
            "backers": "2", 
            "name": "Chad Gaytan", 
            "currency": "USD", 
            "link": "https://www.kickstarter.com/projects/2086765995/motivating-greatness-revolution/", 
            "location": "Sacramento, CA", 
            "totalPledged": "101.0", 
            "description": "Introducing Motivating Greatness Revolution!! the webseries that with your help can change the world!"
        }, 
        {
            "category": "Webseries", 
            "goal": "2200.0", 
            "title": "JUST MAKEDA: A Slightly Alter-ed Webseries by Makeda Declet \u2014 Kickstarter", 
            "backers": "14", 
            "name": "Makeda Declet", 
            "currency": "USD", 
            "link": "https://www.kickstarter.com/projects/2034319893/just-makeda-a-slightly-alter-ed-webseries/", 
            "location": "Los Angeles, CA", 
            "totalPledged": "371.66", 
            "description": "'Cause Everyone's a Little Altered"
        }, 
        {
            "category": "Webseries", 
            "goal": "65000.0", 
            "title": "Word Travel VLOG by Eric Melson \u2014 Kickstarter", 
            "backers": "6", 
            "name": "Eric Melson", 
            "currency": "USD", 
            "link": "https://www.kickstarter.com/projects/1575408382/word-travel-vlog/", 
            "location": "El Paso, TX", 
            "totalPledged": "6.0", 
            "description": "View the entire world through the eyes of a person who has never left the continent.  VLOG viewers will get to vote for activities!"
        }, 
        {
            "category": "Webseries", 
            "goal": "3500.0", 
            "title": "RoomShare by SimpleMan Productions \u2014 Kickstarter", 
            "backers": "47", 
            "name": "SimpleMan Productions", 
            "currency": "USD", 
            "link": "https://www.kickstarter.com/projects/simplemanproductions/roomshare/", 
            "location": "Los Angeles, CA", 
            "totalPledged": "3596.0", 
            "description": "When Scott moves into his new Hollywood studio apartment, it came with more than he expected. A roommate."
        }, 
        {
            "category": "Webseries", 
            "goal": "15450.0", 
            "title": "\"Bus Stop Monologues\" The Webseries by Conroe Brooks \u2014 Kickstarter", 
            "backers": "38", 
            "name": "Conroe Brooks", 
            "currency": "USD", 
            "link": "https://www.kickstarter.com/projects/282352032/bus-stop-monologues-the-webseries/", 
            "location": "Los Angeles, CA", 
            "totalPledged": "3525.0", 
            "description": "We do famous monologues at bus stops for unsuspecting people."
        }, 
        {
            "category": "Webseries", 
            "goal": "9000.0", 
            "title": "The New Adventures of Peter and Wendy by Kyle Walters \u2014 Kickstarter", 
            "backers": "162", 
            "name": "Kyle Walters", 
            "currency": "USD", 
            "link": "https://www.kickstarter.com/projects/thekylewalters/the-new-adventures-of-peter-and-wendy/", 
            "location": "Los Angeles, CA", 
            "totalPledged": "9230.0", 
            "description": "A hilarious and touching modern adaptation of JM Barrie's \"Peter and Wendy\".  Peter Pan, Wendy Darling, Tinkerbell, and more!"
        }, 
        {
            "category": "Webseries", 
            "goal": "2100.0", 
            "title": "KEYBOARD ACHIEVEMENTS. by Jonathan Miraval and Alec Peckham \u2014 Kickstarter", 
            "backers": "2", 
            "name": "Jonathan Miraval and Alec Peckham", 
            "currency": "USD", 
            "link": "https://www.kickstarter.com/projects/1441924049/keyboard-achievements/", 
            "location": "Aurora, CO", 
            "totalPledged": "31.0", 
            "description": "Help us create our web series MIDDLE GROUND, a comedic action filled  series, set in the fictional world of minecraft."
        }, 
        {
            "category": "Webseries", 
            "goal": "12000.0", 
            "title": "Super Academy: A Superhero Comedy Webseries by Ben Lifson \u2014 Kickstarter", 
            "backers": "150", 
            "name": "Ben Lifson", 
            "currency": "USD", 
            "link": "https://www.kickstarter.com/projects/benlifson/super-academy-a-superhero-comedy-webseries/", 
            "location": "Minneapolis, MN", 
            "totalPledged": "7214.0", 
            "description": "At the worlds greatest college for superheroes, follow the adventures of Powerkid and Dark Cop in this weekly web series."
        }, 
        {
            "category": "Webseries", 
            "goal": "800.0", 
            "title": "On The Other Side [Mini-Series] by Melissa Bennett \u2014 Kickstarter", 
            "backers": "20", 
            "name": "Melissa Bennett", 
            "currency": "USD", 
            "link": "https://www.kickstarter.com/projects/420980993/on-the-other-side-mini-series/", 
            "location": "Cape Carteret, NC", 
            "totalPledged": "800.0", 
            "description": "A 7 episode mini series written, directed, filmed, and edited by the teens of Western Carteret Public Library!"
        }, 
        {
            "category": "Webseries", 
            "goal": "1200.0", 
            "title": "Cajun Kids Talk Webseries by Blaine Courteaux \u2014 Kickstarter", 
            "backers": "2", 
            "name": "Blaine Courteaux", 
            "currency": "USD", 
            "link": "https://www.kickstarter.com/projects/974463188/cajun-kids-talk-webseries/", 
            "location": "Thibodaux, LA", 
            "totalPledged": "75.0", 
            "description": "A web series, where I will be interviewing Cajun Kids on Various Topics. Children really do say the darndest things."
        }, 
        {
            "category": "Webseries", 
            "goal": "65000.0", 
            "title": "Rxurrection by Victor Hollingsworth \u2014 Kickstarter", 
            "backers": "37", 
            "name": "Victor Hollingsworth", 
            "currency": "USD", 
            "link": "https://www.kickstarter.com/projects/victorhollingsworth/rxurrection", 
            "location": "Atlanta, GA", 
            "totalPledged": "11597.0", 
            "description": "Four dead people, resurrected. Two good, two evil. What will they do?"
        }, 
        {
            "category": "Webseries", 
            "goal": "1000.0", 
            "title": "RomCom: Sexy Funny Internet Series About Love by Tom Konkle \u2014 Kickstarter", 
            "backers": "23", 
            "name": "Tom Konkle", 
            "currency": "USD", 
            "link": "https://www.kickstarter.com/projects/safetygeeks/romcom-a-twisted-funny-internet-series-on-love-and/", 
            "location": "Hollywood, Los Angeles, CA", 
            "totalPledged": "1356.0", 
            "description": "Tom Konkle and Brittney Powell star in a series that's a lot like herpes, most of the time it's good, but it has occasional flareups."
        }, 
        {
            "category": "Webseries", 
            "goal": "1000.0", 
            "title": "My Elf Report - Customizable Holiday Elf Video Experience by Stephen Luikart & Aaron Janke \u2014 Kickstarter", 
            "backers": "8", 
            "name": "Stephen Luikart & Aaron Janke", 
            "currency": "USD", 
            "link": "https://www.kickstarter.com/projects/myelfreport/my-elf-report-customizable-holiday-elf-video-exper", 
            "location": "New Port Richey, FL", 
            "totalPledged": "195.0", 
            "description": "My Elf Report is a unique, customizable Christmas video to enchant your child's holiday season.  We need your support!"
        }, 
        {
            "category": "Webseries", 
            "goal": "10000.0", 
            "title": "KICKBALLERS by Artopia Pictures \u2014 Kickstarter", 
            "backers": "106", 
            "name": "Artopia Pictures", 
            "currency": "USD", 
            "link": "https://www.kickstarter.com/projects/574840355/kickballers-0/", 
            "location": "Los Angeles, CA", 
            "totalPledged": "11633.0", 
            "description": "What happens when two exes wrangle a band of misfits for another shot at kickball glory? Hilariousness, of course."
        }, 
        {
            "category": "Webseries", 
            "goal": "10000.0", 
            "title": "The Upside of Down by Claire Dellamar and Tamara Perry \u2014 Kickstarter", 
            "backers": "160", 
            "name": "Claire Dellamar and Tamara Perry", 
            "currency": "USD", 
            "link": "https://www.kickstarter.com/projects/180522006/the-upside-of-down/", 
            "location": "Los Angeles, CA", 
            "totalPledged": "10021.09", 
            "description": "Who knew losing everything could be this fun!"
        }, 
        {
            "category": "Webseries", 
            "goal": "9000.0", 
            "title": "What I Learned Today by Kevin Thornburg \u2014 Kickstarter", 
            "backers": "1", 
            "name": "Kevin Thornburg", 
            "currency": "USD", 
            "link": "https://www.kickstarter.com/projects/596723563/what-i-learned-today/", 
            "location": "Albuquerque, NM", 
            "totalPledged": "10.0", 
            "description": "What I Learned Today is a web series where I teach you tutorials and random facts that I learned that day."
        }, 
        {
            "category": "Webseries", 
            "goal": "22000.0", 
            "title": "The Story Occult -horror webseries by 13 year old filmmakers by Ryan Henry \u2014 Kickstarter", 
            "backers": "7", 
            "name": "Ryan Henry", 
            "currency": "USD", 
            "link": "https://www.kickstarter.com/projects/913147832/the-story-occult-a-horror-thriller-anthology-webse/", 
            "location": "Washington, DC", 
            "totalPledged": "460.0", 
            "description": "An anthology horror/thriller webseries that features stories of the paranormal, slashers, and things that go bump in the night."
        }, 
        {
            "category": "Webseries", 
            "goal": "3500.0", 
            "title": "Capt Ralph's Seafood Safari sizzle project by Capt Ralph Towlen \u2014 Kickstarter", 
            "backers": "47", 
            "name": "Capt Ralph Towlen", 
            "currency": "USD", 
            "link": "https://www.kickstarter.com/projects/1254305025/capt-ralphs-seafood-safari-new-3-4-min-trailer/", 
            "location": "Shinnecock Hills, Southampton, NY", 
            "totalPledged": "3570.0", 
            "description": "High adventure quest for 50lbs of sustainable seafood for a professional cooking class. Caught spearfishing on shipwrecks or rod & reel"
        }, 
        {
            "category": "Webseries", 
            "goal": "15000.0", 
            "title": "Tourist X by Juwan Chung \u2014 Kickstarter", 
            "backers": "7", 
            "name": "Juwan Chung", 
            "currency": "USD", 
            "link": "https://www.kickstarter.com/projects/juwanuno/tourist-x-0/", 
            "location": "Los Angeles, CA", 
            "totalPledged": "425.0", 
            "description": "A guerilla travel show at it's classiest."
        }, 
        {
            "category": "Webseries", 
            "goal": "50000.0", 
            "title": "THE 3 BITS web series by Margaret Singer \u2014 Kickstarter", 
            "backers": "312", 
            "name": "Margaret Singer", 
            "currency": "USD", 
            "link": "https://www.kickstarter.com/projects/1352833174/the-3-bits/", 
            "location": "Brooklyn, NY", 
            "totalPledged": "50590.0", 
            "description": "Help us combat the mainstream destruction of everything weird and wonderful!"
        }, 
        {
            "category": "Webseries", 
            "goal": "5500.0", 
            "title": "Help Fund a CES hands on series! by Ryan Scalia \u2014 Kickstarter", 
            "backers": "1", 
            "name": "Ryan Scalia", 
            "currency": "USD", 
            "link": "https://www.kickstarter.com/projects/scalia72/help-fund-a-ces-hands-on-series/", 
            "location": "Las Vegas, NV", 
            "totalPledged": "10.0", 
            "description": "The Consumer Electronics Show (CES) is Coming again in 2014. Get to see all of the Gear in great detail through this YouTube series."
        }, 
        {
            "category": "Webseries", 
            "goal": "2500.0", 
            "title": "PUMPED by Owen Harn \u2014 Kickstarter", 
            "backers": "0", 
            "name": "Owen Harn", 
            "currency": "USD", 
            "link": "https://www.kickstarter.com/projects/509842358/pumped/", 
            "location": "Largo, FL", 
            "totalPledged": "0.0", 
            "description": "A raunchy new comedy about what it's like living unfiltered...for all those things you really wanna say to people."
        }, 
        {
            "category": "Webseries", 
            "goal": "850.0", 
            "title": "\"SPARK\" Dark Things (Episode 2 of 6) by Naathan Phan \u2014 Kickstarter", 
            "backers": "13", 
            "name": "Naathan Phan", 
            "currency": "USD", 
            "link": "https://www.kickstarter.com/projects/1512973746/spark-dark-things-episode-2-of-6/", 
            "location": "Orange, CA", 
            "totalPledged": "860.25", 
            "description": "\"Dark Things\" is an original dark fantasy/sci-fi about supernatural creatures, man-kind, and the one entity in between: Gerald."
        }, 
        {
            "category": "Webseries", 
            "goal": "10000.0", 
            "title": "Hello World! An Educational & Entertaining Puppet Show by The Hello World Program \u2014 Kickstarter", 
            "backers": "71", 
            "name": "The Hello World Program", 
            "currency": "USD", 
            "link": "https://www.kickstarter.com/projects/1784712961/hello-world-an-educational-and-entertaining-puppet/", 
            "location": "Los Angeles, CA", 
            "totalPledged": "5077.0", 
            "description": "The Hello World Program is a series of videos & tutorials teaching computer science, programming, & digital media to kids of all ages."
        }, 
        {
            "category": "Webseries", 
            "goal": "10000.0", 
            "title": "\"The Art Of Acting Out\" Kickstarter Campaign by The Art Of Acting Out \u2014 Kickstarter", 
            "backers": "246", 
            "name": "The Art Of Acting Out", 
            "currency": "USD", 
            "link": "https://www.kickstarter.com/projects/1543547486/the-art-of-acting-out-kickstarter-campaign/", 
            "location": "Denver, CO", 
            "totalPledged": "10251.91", 
            "description": "Phil Collins (the barista) quits his day job to follow his dream of becoming an actor... Sort of."
        }, 
        {
            "category": "Webseries", 
            "goal": "5000.0", 
            "title": "VCR by VCR the Series \u2014 Kickstarter", 
            "backers": "11", 
            "name": "VCR the Series", 
            "currency": "USD", 
            "link": "https://www.kickstarter.com/projects/vcr/vcr/", 
            "location": "Los Angeles, CA", 
            "totalPledged": "395.0", 
            "description": "VCR chronicles the mis-adventures of two twenty somethings living together in Los Angeles.  But they are not actors..."
        }
    ]
}